<?xml version="1.0"?>
<!-- SCPlusV2_RS232 -->
<SBEDataUploadFile>
<ApplicationData>
<SeatermAF>
<SoftwareVersion>2.1.4</SoftwareVersion>
<BuildDate>11-Sep-2013 15:42:25 GMT</BuildDate>
</SeatermAF>
</ApplicationData>
<InstrumentState>
<HardwareData DeviceType='SBE19plus' SerialNumber='01907141'>
   <Manufacturer>Sea-Bird Electronics, Inc.</Manufacturer>
   <FirmwareVersion>2.5.2</FirmwareVersion>
   <FirmwareDate>12 Mar 2013 11:50</FirmwareDate>
   <CommandSetVersion>1.3</CommandSetVersion>
   <PCBAssembly PCBSerialNum='44566' AssemblyNum='41054G'/>
   <PCBAssembly PCBSerialNum='43709' AssemblyNum='41580B'/>
   <PCBAssembly PCBSerialNum='42732' AssemblyNum='41606'/>
   <PCBAssembly PCBSerialNum='42178' AssemblyNum='41059D'/>
   <MfgDate> 12 JUL 2012</MfgDate>
   <InternalSensors>
      <Sensor id='Main Temperature'>
         <type>temperature0</type>
         <SerialNumber>01907141</SerialNumber>
      </Sensor>
      <Sensor id='Main Conductivity'>
         <type>conductivity-0</type>
         <SerialNumber>01907141</SerialNumber>
      </Sensor>
      <Sensor id='Main Pressure'>
         <type>strain-0</type>
         <SerialNumber>3671365</SerialNumber>
      </Sensor>
   </InternalSensors>
   <ExternalSensors>
      <Sensor id='volt 0'>
         <type>not assigned</type>
         <SerialNumber>not assigned</SerialNumber>
      </Sensor>
      <Sensor id='volt 1'>
         <type>not assigned</type>
         <SerialNumber>not assigned</SerialNumber>
      </Sensor>
      <Sensor id='volt 2'>
         <type>not assigned</type>
         <SerialNumber>not assigned</SerialNumber>
      </Sensor>
      <Sensor id='volt 3'>
         <type>not assigned</type>
         <SerialNumber>not assigned</SerialNumber>
      </Sensor>
      <Sensor id='volt 4'>
         <type>not assigned</type>
         <SerialNumber>not assigned</SerialNumber>
      </Sensor>
      <Sensor id='volt 5'>
         <type>not assigned</type>
         <SerialNumber>not assigned</SerialNumber>
      </Sensor>
      <Sensor id='serial'>
         <type>not assigned</type>
         <SerialNumber>not assigned</SerialNumber>
      </Sensor>
   </ExternalSensors>
</HardwareData>
<StatusData DeviceType='SBE19plus' SerialNumber='01907141'>
   <DateTime>2022-08-08T18:53:37</DateTime>
   <LoggingState>not logging</LoggingState>
   <EventSummary numEvents='0'/>
   <Power>
      <vMain>12.3</vMain>
      <vLith>7.9</vLith>
      <iMain>61.0</iMain>
      <iPump>40.6</iPump>
      <iExt01>17.5</iExt01>
      <iExt2345>55.2</iExt2345>
   </Power>
   <MemorySummary>
      <Bytes>1135839</Bytes>
      <Samples>59781</Samples>
      <SamplesFree>3403279</SamplesFree>
      <SampleLength>19</SampleLength>
      <Profiles>26</Profiles>
   </MemorySummary>
</StatusData>
<ConfigurationData DeviceType='SBE19plus' SerialNumber='01907141'>
   <ProfileMode>
      <ScansToAverage>1</ScansToAverage>
      <MinimumCondFreq>3180</MinimumCondFreq>
      <PumpDelay>40</PumpDelay>
      <AutoRun>no</AutoRun>
      <IgnoreSwitch>no</IgnoreSwitch>
   </ProfileMode>
   <Battery>
      <Type>alkaline</Type>
      <CutOff>7.5</CutOff>
   </Battery>
   <DataChannels>
      <ExtVolt0>yes</ExtVolt0>
      <ExtVolt1>yes</ExtVolt1>
      <ExtVolt2>yes</ExtVolt2>
      <ExtVolt3>yes</ExtVolt3>
      <ExtVolt4>no</ExtVolt4>
      <ExtVolt5>no</ExtVolt5>
      <SBE38>no</SBE38>
      <WETLABS>no</WETLABS>
      <OPTODE>no</OPTODE>
      <SBE63>no</SBE63>
      <GTD>no</GTD>
   </DataChannels>
   <EchoCharacters>yes</EchoCharacters>
   <OutputExecutedTag>yes</OutputExecutedTag>
   <OutputFormat>converted HEX for AFM</OutputFormat>
</ConfigurationData>
<CalibrationCoefficients DeviceType='SBE19plus' SerialNumber='01907141'>
   <Calibration format='TEMP1' id='Main Temperature'>
      <SerialNum>01907141</SerialNum>
      <CalDate>21-Jan-21</CalDate>
      <TA0>1.249193e-03</TA0>
      <TA1>2.797474e-04</TA1>
      <TA2>-1.985076e-06</TA2>
      <TA3>2.160070e-07</TA3>
      <TOFFSET>0.000000e+00</TOFFSET>
   </Calibration>
   <Calibration format='WBCOND0' id='Main Conductivity'>
      <SerialNum>01907141</SerialNum>
      <CalDate>21-Jan-21</CalDate>
      <G>-9.922252e-01</G>
      <H>1.384500e-01</H>
      <I>-2.398256e-04</I>
      <J>3.771994e-05</J>
      <CPCOR>-9.570000e-08</CPCOR>
      <CTCOR>3.250000e-06</CTCOR>
      <CSLOPE>1.000000e+00</CSLOPE>
   </Calibration>
   <Calibration format='STRAIN0' id='Main Pressure'>
      <SerialNum>3671365</SerialNum>
      <CalDate>11-Jan-21</CalDate>
      <PA0>4.836523e-02</PA0>
      <PA1>1.550014e-03</PA1>
      <PA2>6.745238e-12</PA2>
      <PTCA0>5.249480e+05</PTCA0>
      <PTCA1>3.441759e+00</PTCA1>
      <PTCA2>-9.030937e-02</PTCA2>
      <PTCB0>2.497925e+01</PTCB0>
      <PTCB1>2.500000e-04</PTCB1>
      <PTCB2>0.000000e+00</PTCB2>
      <PTEMPA0>-6.834595e+01</PTEMPA0>
      <PTEMPA1>5.344906e+01</PTEMPA1>
      <PTEMPA2>-6.085179e-01</PTEMPA2>
      <POFFSET>0.000000e+00</POFFSET>
      <PRANGE>5.080000e+02</PRANGE>
   </Calibration>
   <Calibration format='VOLT0' id='Volt 0'>
      <OFFSET>-4.580527e-02</OFFSET>
      <SLOPE>1.250734e+00</SLOPE>
   </Calibration>
   <Calibration format='VOLT0' id='Volt 1'>
      <OFFSET>-4.607369e-02</OFFSET>
      <SLOPE>1.250389e+00</SLOPE>
   </Calibration>
   <Calibration format='VOLT0' id='Volt 2'>
      <OFFSET>-4.635158e-02</OFFSET>
      <SLOPE>1.251102e+00</SLOPE>
   </Calibration>
   <Calibration format='VOLT0' id='Volt 3'>
      <OFFSET>-4.594527e-02</OFFSET>
      <SLOPE>1.249890e+00</SLOPE>
   </Calibration>
   <Calibration format='VOLT0' id='Volt 4'>
      <OFFSET>-4.646000e-02</OFFSET>
      <SLOPE>1.251042e+00</SLOPE>
   </Calibration>
   <Calibration format='VOLT0' id='Volt 5'>
      <OFFSET>-4.693158e-02</OFFSET>
      <SLOPE>1.251159e+00</SLOPE>
   </Calibration>
   <Calibration format='FREQ0' id='external frequency channel'>
      <EXTFREQSF>9.999972e-01</EXTFREQSF>
   </Calibration>
</CalibrationCoefficients>
<EventCounters DeviceType='SBE19plus' SerialNumber='01907141'>
   <EventSummary numEvents='0'/>
</EventCounters></InstrumentState>
<CastHeader>
<![CDATA[
DH26,26
cast  26 08 Aug 2022 18:39:55 samples 57665 to 59781, avg = 1, stop = mag switch
<Executed/>]]>
</CastHeader>
<UserHeaderInsert>
<![CDATA[

** Platform: M. Perley 
** Cruise: Per2022473 
** Station:  ESI-06
** Cast: 01 
** Latitude: N  44 46.3308
** Longitude: W 62 26.1203
** Sounding: 40.3
** Chief Scientist: Ryan Stanley 
** Comment: 
]]>

</UserHeaderInsert>
<InstrumentRawData>
<SBEDataUpload startAddr='1095616'>
   <Type>1</Type>
   <DataFormat>SEACATPLUS0</DataFormat>
   <Bytes>40223</Bytes>
   <Data>
1CC1047C840A492708CA51FCAEC78ADB
1CD4121CC10472840A4A2708CA51FDAE
CA8AD11C6D121EC1046A840A482708CA
51F7AECC8AD41C16131EC1045D840A47
2708CB510BAFC58ACD1CA9121CC1044E
840A472708CB51FCAEBC8AC31CF2121D
C1043F840A472708CC510EAFC28AD71C
AB121EC1042E840A472708CC5104AFC0
8AE31CC8121CC1041E840A462708CC51
07AFB48AD11CE5121DC10411840A4627
08CD51FEAEC08ACD1CFF121DC1040884
0A452708CD5108AFB38ACE1CC4121BC1
04FD830A462708CE5100AFC38ACA1C90
121EC104FC830A462708CF51FAAEC78A
CD1CF8121CC104FC830A462708CF51FE
AEC88AD01CD9121EC10400840A452708
D05107AFBE8ACE1CC1121EC10404840A
472708D051FFAEDA8ACB1C0E131EC104
0E840A472708D151FCAED48AC71CC212
1EC10419840A462708D151FDAEC98ABF
1CAF121DC10427840A482708D251FDAE
CD8AD31CCB1220C10432840A462708D3
51FDAED48ABB1CD21220C1043D840A47
2708D351FEAECE8AC01C15131EC1044A
840A472708D351FFAEC48AC51CB5121F
C10457840A482708D351FEAEBF8AD31C
A0121EC1045E840A472708D451F5AEB8
8ADE1CB1121DC10465840A482708D451
FEAEAE8ACA1C5B131DC10466840A4827
08D45104AFAD8AE11CEF121AC1046684
0A482708D551FCAEBF8ADE1CBB1219C1
0462840A472708D55101AFB28AB91CD7
1218C1045E840A452708D55102AFB08A
B71C9A1217C10455840A462708D65104
AFB58AB81CFE1219C1044C840A472708
D651F7AEB78AAF1CEF1217C10443840A
472708D75109AFB48AC51C1D1316C104
39840A462708D85100AFA98AB91C1D13
17C10431840A462708D851F9AEB18AC5
1CA71217C10427840A452708D85100AF
B98AD81C121318C10420840A462708D8
5100AFBC8AB41CC41218C10414840A45
2708D85104AFC28AC01CA91217C1040C
840A452708D851FCAEC08AE81C9B1218
C10404840A452708D85107AFC98AD11C
C21217C10406840A452708D851F9AEC1
8AD01C881216C104FC830A462708D851
00AFCF8AD41CAF1216C104FC830A4527
08D8510AAFD58AD41CC31216C104FF83
0A462708D95102AFD28ADF1C991218C1
0404840A462708D95104AFD18AF51CAA
1218C1040A840A462708D951F3AED18A
E11C911218C10418840A462708DA5102
AFD28AD41CD61219C10424840A452708
DA5106AFCA8ABA1CE11219C10435840A
472708DA51F8AEC78ABE1CD41218C104
47840A472708DA5105AFC88AD91C0B13
15C10457840A462708DA51F8AECB8ACC
1CB91212C10463840A462708DB510FAF
C28AD11C8A1211C1046A840A462708DC
51FCAED78ABE1CB71210C10468840A47
2708DC5106AFD68ADD1CCD1212C10465
840A472708DC5103AFD28AC91C271313
C10459840A462708DD5100AFD58AB81C
BA1210C1044C840A462708DD51FCAEDA
8AE91CB41212C1043F840A462708DE51
02AFD28AC71C321313C10435840A4627
08DE51FDAEE38AF01CC11212C1042D84
0A462708DE5105AFE58AD81CE31212C1
0424840A462708DE51FAAEE48AD51C85
1212C1041C840A462708DE5105AFE48A
C01CCD1212C10418840A452708DE510E
AFDB8AD41CEB1211C10414840A462708
DE5102AFDD8AD91CC01211C10411840A
452708DF5102AFE58ACA1C101311C104
10840A432708E05100AFEC8AC61C8412
11C1040F840A452708DF5106AFEC8AC4
1C861212C10412840A462708E0510CAF
F58ACC1CF81215C10414840A452708E0
5107AFF88ACD1CB71212C1041A840A44
2708E051F3AEEA8ADC1C781213C1041D
840A452708E05108AFEE8AC11CC11214
C10425840A472708E1510DAFED8AC91C
D81213C10429840A452708E251FCAEFA
8AC61C4E1211C1042D840A472708E251
FDAEFD8AB41CAD1213C10430840A4527
08E251FDAE018BD01CD71212C1042F84
0A462708E35104AF038BD91CD41211C1
042E840A452708E451F1AE058BC71CCA
1211C10429840A452708E451FAAE068B
DB1CC41212C10424840A462708E55111
AF058BCD1CB81213C10420840A452708
E5510BAF0B8BCC1CE81210C1041D840A
452708E4510DAF0C8BDB1C211313C104
1E840A462708E55108AF0E8BC71CE312
12C10422840A472708E551F9AE138BAE
1CE21214C10427840A472708E551EDAE
148BE31CAF1211C10434840A472708E5
5102AF108BCB1CF11213C10442840A45
2708E55103AF0E8BC31C121311C1044F
840A462708E551FCAE0E8BC81CCB1211
C1045A840A472708E55102AF028BE11C
BE120FC1045E840A462708E5510CAFFA
8AEE1CBA120EC1045C840A472708E551
FEAEF98ACC1CED120BC10459840A4627
08E551FCAEEF8AE01CF4120CC1045084
0A452708E451F4AEE88AD71C2F130BC1
0443840A452708E55113AFE78AD41CBC
120CC10437840A462708E551FCAEE88A
D31CC0120BC10427840A452708E55104
AFE78AD41C4F1208C10416840A452708
E55104AFE68AF51CBE1209C10406840A
442708E55107AFE58ACC1CD11207C104
F8830A452708E551FBAEEC8AEE1CD312
08C104EC830A442708E55109AFEA8ADF
1CA61206C104E5830A452708E65104AF
E58AC11C711207C104DF830A442708E6
51FCAEE38AC51C9E1208C104DC830A44
2708E65101AFEA8ACB1CB61209C104DD
830A452708E751F9AEF08AC51C191309
C104E2830A472708E65102AFEB8AD61C
DF1208C104EA830A452708E65107AFEE
8A001DEE120AC104F8830A442708E651
FBAEEB8AEC1CF5120AC10408840A4527
08E65105AFEC8AE31C161209C1041984
0A472708E7510DAFE78ADC1C041209C1
042F840A462708E75105AFE98ADA1CC6
1208C1043E840A462708E751FEAEE98A
E41CBC1207C1044F840A462708E751F4
AEE18ACC1C5D1407C1045F840A472708
E751FCAEE08AE11C681306C10466840A
462708E85102AFDE8ADD1C1F1306C104
6F840A482708E851F9AEDD8ACD1C0113
07C10474840A462708E85104AFDE8AE9
1CB81204C10471840A462708E851FEAE
E18ACF1C9C1204C10455840A462708E9
51FEAEDA8AD61C961203C1044F840A46
2708E85107AFC88ADB1C961202C10455
840A452708E85113AFC08AF71C661202
C1044B840A462708E95104AFC38AED1C
AA1201C10435840A442708E95106AFC8
8AD91CE112FFC00425840A442708EA51
00AFC28AD61CC21200C1040F840A4427
08EA5101AFB98ADF1CD712FCC0041084
0A442708EA5102AFA68ACE1C9212F8C0
04F1830A452708EA51F8AE978ADA1C87
12F5C004C3830A452708EA51F1AE948A
E11CE912F1C00498830A422708EA51F6
AE718AD61CBD12EEC0047E830A422708
E951F3AE658AE31CD912E7C00472830A
432708E95105AF558AE71CC812E5C004
75830A442708EA5103AF558AD51CF812
E2C0044F830A442708EA51FDAE5A8ABA
1CBC12E3C0044F830A452708EB5102AF
5C8AD61CBA12E6C00454830A452708EB
51F2AE638ACC1CD412E6C00443830A45
2708EC5101AF738ACC1CFC12E2C0044D
830A452708EB51FEAE6E8AD91C8F12DE
C0044B830A452708EB51FBAE7D8ADC1C
A912DDC0043C830A462708EC51F7AE80
8AC41C9112E0C0042A830A462708EB51
E6AE8B8AC31CC912DFC00420830A4727
08EC51FBAE8F8AD41CBA12E1C0041A83
0A452708EB51F9AEA08AC01C7E12DCC0
0412830A472708EB51F3AEA48ADE1C17
13DBC00401830A452708EA51EEAE9E8A
E11C8412D6C004E4820A452708EA5104
AF9C8AF91C3B13D0C004D2820A472708
EB51F8AE958ACE1C6F12C8C004CE820A
452708EB51FAAE898ACC1C8F12BAC004
C4820A472708EA51F7AE7F8ADA1CB812
ACC004C7820A462708EA51F3AE7B8AF5
1CCD129CC004B4820A442708EB51F7AE
7C8AD01CCB128EC004A7820A432708EA
51FBAE798ACE1C8C1283C004A8820A44
2708EA51F9AE758ACC1C9D127DC004AB
820A452708EA5109AF6D8AE91CE21279
C004B6820A442708EA51FDAE7A8AD61C
CC1278C004BA820A442708E951FCAE7A
8ABA1C8E1278C004B7820A442708E951
FCAE838AB81CE5127DC004AA820A4227
08E951F7AE868AB21CD01280C004A782
0A442708E9510BAF938ACB1CAE1283C0
049B820A462708E951FCAE8D8AE01CF6
1285C00494820A462708E951F3AE8D8A
D41CA71288C00487820A452708E951F9
AE8C8AD71CC01287C0047D820A442708
E951ECAE938AC01CAB1387C0046F820A
452708EA51FCAE918ACA1CE2FE87C004
6A820A452708EA51F9AE948AC01CDCFE
7BC00465820A452708EB51F9AE9B8AD0
1CE7FE6DC00465820A442708EA51F3AE
9D8AC71CE0FE66C00465820A442708EB
51F7AEA18AB41CE2FE65C0046C820A47
2708EB51F5AEA38AC81CD5FE64C00473
820A472708EB51F4AEAA8ACC1CE4FE66
C00488820A462708EB51F7AEAF8AD81C
E9FE64C00483820A482708EB5101AFB6
8ACA1CE6FE62C0047D820A472708EB51
FBAEA78AB81C372D55C00477820A4527
08EC51F9AEA68ACC1C0E1D45C0047D82
0A462708EE51F7AE8E8AC11CA11B30C0
0481820A462708ED51FFAE7E8AC51C5E
1926C0047C820A462708ED51FBAE6E8A
D21C2D1823C0048B820A462708EE51F3
AE6E8ACA1CF91625C004DC820A462708
EE5105AF6E8ABF1CF31525C0045D830A
452708ED5108AF7B8AD01C311529C004
B2830A442708ED5106AF7B8AB71CCF14
2EC004DD830A442708ED51FCAE888AC9
1C6C1433C00404840A442708EC5101AF
888ABA1C1B1435C00420840A442708EC
5102AF958ACC1C181439C00406840A45
2708EC5109AF978ACA1CAE1337C0043D
840A462708ED5109AF9C8ABA1CF01338
C00450840A452708ED5100AF958AC71C
62143BC00441840A442708EF5102AF93
8AAD1CD8133DC00461840A452708EE51
F4AE798AC21C4A133EC00468840A4427
08EF51F9AE648AC71CAD133CC0045E84
0A442708EF5103AF3F8ADE1C75133DC0
0478840A422708EF51FBAE368AC51C7A
1336C00458840A442708EE51F1AE178A
C01C49132FC0045E840A452708EF51FC
AEF489BA1C4C131FC004A0840A442708
EF51F9AED089BB1C3C1316C004A9840A
452708F051F9AEB389BD1C751312C004
94840A452708F05107AF3B8AB21C6313
6CC2041F86148B2708F051FDAE5B8C80
18631340E2045BFF15D72708EF51F9AE
B58D4F142713370505D69D15FC2708F0
51EFAE728E40143013961D05E90F160C
2808F051F7AEE88E08133C13113005E1
D3164E2808F051FEAE288F4713251334
3D05E3D616E72808F051E7AE4D8FAF12
7174C4460554D416C02908F051ECAE69
8FC212D20A334D053CD116A52A08EF51
1CAF778FC612D00A0C5305CDCC16722B
08EE519FAF828F1A14650A0F5D05CCD7
16BF2B08EF5186B0858F5613760A4860
0505E016B72B08EE51B2B1898F5A139F
0AA95A0562E5168C2B08EF5147B3898F
5E137F0A46550586E516452B08EF51AD
B48D8F5E13570A835105B2E216DE2A08
EF51E3B5838F9D137E0A574F0529E016
6B2A08EE51B8B68B8F7C135C0AAF5105
A3D216012A08EE5140B78E8FF9126A0A
D15705EECA16B82908EF5171B7908F47
14580AAD5C05C5CB16972908EF5139B7
8E8F4E13530AC55E051FD116942908EF
51DFB6898F39134E0A325F05CEDB169F
2908EF516AB68A8FCF12640A375F05B1
DB16B32908EF51F6B58C8FAE13FF0951
5F0572D416E02908F05199B58A8F4F13
9C0A415F05CBD016242A08F0514DB591
8F6113790A265E0595D2167D2A08EF51
16B58D8FA913920AE55B05AFD316DD2A
08F05115B5988F8E14330A045A0579D4
16412B08F05133B58A8F5113B80AE559
05B1D216A62B08F2514AB4898F3E1360
0A365B05BBCF16062C08F151F1B3908F
E8137C0AB65E05E8CB16572C08F05147
B4938F8813360A756405B8C816942C08
F05127B48C8F89135F0A676B05F3C616
B52C08F151B2B3948FA913620AC77305
3BC216B42C08F151ECB2998F1C14330A
2F7A05CEB4169A2C08F151DCB1948F41
136B0A387E057CAE166B2C08F251CCB0
928F0414C70A6F8105A2AC16312C08F1
51A8AF938FC8123C0A6381056EB016F6
2B08F15167AE948FC4133B0A197E0561
B516C12B08F15121AD988FC214430A18
7B05F0B916942B08F151DAAB938F3914
AC0AFF78051FC4166C2B08F15176AA95
8FFD147A0A827705E0CD163F2B08F251
69A9978F6B13560A6F760590CB16092B
08F25126A8968F7F13430AAD750574C3
16C42A08F15100A7968F8013880A0975
0565BF16772A08F051C8A5948F011543
0A6F7405A5BD16232A08F1519DA4948F
55135B0A037305BDBD16CF2908F251BE
A3958FDF12940AF4700518BF167C2908
F251FAA28B8F0F14760AC56E05A4C016
382908F1512BA2928F33133E0AC56C05
6CC216082908F15154A1908F44135E0A
006B0518C416F42808F15167A08E8FB5
149A0AA26905EEC516092908F051819F
948F3D14200A67680582C616442908F1
51A49E898F4B15770A49670535C616A2
2908F151C49D8D8FDA13670A496605C5
C616252A08F051179D948F3614960AA0
6405F0C716C22A08F051849C898FBC13
2E0A666205CBC9166C2B08EF51259C8F
8FD013B60A23600553CD161B2C08EF51
D59B8E8F8213750AAB5E05E3D816AD2C
08F0517C9B938FCC13060A8C5D0507DE
16232D08F151189B928F2813610A005B
05B7DC167F2D08F151949A8D8F87132B
0A77560543DB16B52D08F151F2998C8F
FB13220A6A52053DDB16C32D08F05160
998E8FCF13610AAF4E050CDA16AB2D08
F051D398918F0314570A2D4D05F1D816
6D2D08F05165988C8FC313510AEB4D05
05D2163D2D08F2511598988F0514600A
D4550532D816F92C08F1510F98998F2C
147C0A405E0595DE16732C08F1512E98
948F8A142809A16205CEDE16D52B08F2
517598928F5C13BA0A5563051CD31641
2B08F351F398908F0213440ACE640511
C416DE2A08F3516699898F5C14800A42
6905BFD416732A08F4513B9A8D8FC914
620ACB6C05C9D916EF2908F551019B92
8F61148C0ACF6D05AFD516762908F451
DA9B928F2413550A286E05B3CF161629
08F451BB9C928F8413E40AE76E052CC9
16E12808F551719D908F3013770A0B70
057AB816292908F451069E938FB61357
0AB66F05CCC616342A08F451549E8D8F
1113880A146905F9C516F12A08F55193
9E8E8F9613F5097B6205A7C916F22B08
F551FD9E968F9213980A715E0523CB16
FF2C08F651919F968F88144F0AC05E05
3DCC16E02D08F55114A08E8F92142E0A
C46305ADCC16A22E08F551A9A08A8F2D
14BF0ADF660542CC162F2F08F6511AA1
8C8FFC144C0AB56405DBCC168B2F08F5
5167A18F8FFB139F0AD65F0590CE16B4
2F08F551C3A18B8F4F14310A765C05D4
CF16AE2F08F55176A2958F8F14F90984
5A053FD116802F08F55171A3928F3314
530A88590588D0163F2F08F4518CA499
8FB6144D0A0D590516D016F02E08F551
6AA5968FCA14F90A175B055DD016A12E
08F551EFA5968F9E15330A565F053FD1
164D2E08F4510BA6988F9714190A7062
056CD316F22D08F551EFA5928F471579
0AEC630542D5168C2D08F55191A58F8F
8314F90A186405E0D516212D08F55120
A5908FE113E3098864059FD616B12C08
F351AAA4988FE713860A88650590D516
472C08F3512CA4938F0113240A566605
52D216E72B08F2519CA3908F3813D10A
F9680548CD169E2B08F451E0A2938F90
13170A0B6D05B1C8166B2B08F3511DA2
898FA714EC0A9C7205F1C5164C2B08F4
5147A18E8FFF142F0A70780574C4164A
2B08F4515CA0948FD2135F0A657D0507
C3165D2B08F351759F928FCB13A20A70
8105A1C016872B08F451829E9B8F2415
9A0A27850552B916CD2B08F5518F9D96
8F6B14420A10890552B0162D2C08F651
C09C908FE213DA0A568B05A2AC16992C
08F651E69B948FD9139F0A208B0550B1
16052D08F751FF9A958F5414350A178A
0518C1166A2D08F6511A9A948F2F145E
0A0F8905D8C816CD2D08F8515B99918F
5214270A83880511CE162B2E08F751C6
98908FAA135C0A958505B2CD16872E08
F8515B988F8F94138B0A068305ABC816
E52E08F8511D98958FAC147A0AE47F05
3CC616342F08F9510698948FDE14B30A
BF7D05DCC916742F08F851DE978C8FEE
133F0A857C0562D1169D2F08F751AA97
998FB613350AEF7B0590D316AD2F08F6
513F97A18FC0141A0A83790515D31699
2F08F651D996948FED14550A3A710572
D216602F08F6516496978FEB14470ABD
670560D216002F08F651EE95978F9C14
390AD5600556D2167C2E08F651839598
8F9C141F0A755D0551D116E12D08F651
03959F8FBC14870AD75C05D8CE16322D
08F5519994968F31141A0ABC5D05A1CA
16832C08F4511294948FB013110A325F
05ECC716DE2B08F3517B93928F421360
0A75630574C616462B08F451EA92918F
5B13A60A8D6B0503C116CA2A08F45144
92958F1B137B0A47750590B416782A08
F551B291908F7E133C0ACE7E05B8A116
592A08F4512991908F9213550AE88705
5095167A2A08F451C490938FB8139A0A
C68D05B99616CD2A08F4516990968F7E
134F0A639105139816562B08F4513B90
8C8FDF138A0A0C910595A016F92B08F6
5168908C8F1914670BF88D056D9C16A1
2C08F7517C91968F2814630A148D056B
9F164F2D08F7514E93978F4515270AC1
8B05AF9D16FE2D08F7515795988F1C15
260A908E058C9616972E08F651589794
8F7314350AAA93052595160D2F08F651
4A99908F8F138B0ADB9705419F165E2F
08F751219B8A8F9413340AEB990568A8
168E2F08F851CA9C908F6414830AC99A
0549AA16982F08F8511B9E938FCE1546
0A8795054AA9167E2F08F751129F908F
BC14710A1E8E0569A916472F08F851B3
9F8E8F19143C0A1D880521AA16F82E08
F9510CA08D8F7C14D00AAA8405E5AA16
9B2E08FA5133A0988FBB155C0A4D8205
F4AB163A2E08FB514FA08E8F9514790A
BD8005DBAC16D92D08FB5167A0938F9A
144D0A847F05C7AD16782D08FB5167A0
888F1B14460A8B7E0591AE16162D08FB
515AA0948F5414A10AD17D0536AF16B2
2C08FC5149A08A8FC813550A4A7D05E6
AF164D2C08FB5106A0908F0913860AD2
7C0520B116E82B08FB51DD9F8E8F1714
6B0A6E7C05F1B016882B08FC51B89F92
8FD3137E0A497C059FAC163F2B08FB51
8B9F8F8FC113260A647C05F5A916142B
08FA51359F838F8D133E0AAF7E0509A2
16172B08F951E89E858FCC144D0A6A83
05059B16442B08F951719E948FC1134D
0AEA8505CC9F16A82B08F951009E898F
8B13790AAD84056FA616322C08F95190
9D898F50130B0AFD800536AE16D22C08
F9512B9D8E8F4D14CD0AC87B0511B216
6F2D08F951169D898F6F147D0AA97905
3EAF16FC2D08F851949D8A8FC513FE09
557B0512AD16632E08F751659E898F41
13390A7D7F05B69716A62E08F7511F9F
8D8FFB125E0A458805238316C22E08F7
51969F898F4914220A0594054C8316BC
2E08F551F39F858FC113A30A839B050E
85169E2E08F6517BA08C8FEF14500A61
9E05B385166C2E08F65188A18C8F3A14
8F0A179F05D18716302E08F7510DA385
8F3614620A6E9E05398616FB2D08F751
B8A4838F7015480A4B9E05328616D02D
08F75178A68A8F8E137C0A829E057086
16B32D08F8512CA8818F9214780A6B9E
05D48616A22D08F951E6A9858F421475
0A309E051B87169E2D08F95152AB7F8F
3814800AE09D05078816A02D08F951A8
AC898FE215780A449D05AC8916A02D08
F951C1AD8C8F1F15560A209C056D8B16
972D08F951BCAE8E8FD5135E0A9B9A05
2F8D16842D08F9519FAF838F3A14EE0A
DE98050F8F165F2D08FA517DB0858F19
14500A1C9705E48E162A2D08FB5132B1
878F5713780AEE9505BF9116EB2C08FB
51D9B1878F5C14260A3394050B9516A7
2C08FC515FB2898FA913EA09AC9105F4
95166E2C08FC51E3B2838F3914F50986
8F052497163F2C08FB5158B3908F2614
390AD78D05939916212C08FC51D1B387
8F3614390AC78B05F49D16122C08FB51
33B4858F5813640AE18805C69C16192C
08FD5179B4838F2614220A4F8705C79D
163E2C08FD51C5B4838FA513670A4086
05609F167F2C08FD5100B5868F521462
0A0A8505FF9D16DD2C08FD5132B5858F
2C14850A108505099616472D08FD5166
B5898FB4133F0AEC8705359616B12D08
FC51A7B5838FDC14B10A9F8A059C9216
142E08FC51BAB58C8F41134D0A728D05
9B9116632E08FD51BBB5828F35135A0A
EF8F05E28D16A22E08FD51CDB5838F6D
133D0ABE9205C48A16D02E08FD51E4B5
878F4614760ACD9505B88816EB2E08FC
51F2B5878F01144E0AA49805EA8516F4
2E08FC51F6B57F8F13144E0A3F9B05A9
8516F22E08FC51FAB5858F84135E0A04
9D05C78516E52E08FD5104B6838F9615
8B0AF49D05D48416C92E08FD51F3B581
8FA2137C0AAF9E054885169C2E08FE51
15B6848F7C14480A009F056484165C2E
08FD513AB6848FD314760A5B9F05FD84
16082E08FD514BB6868F2514360A849F
05DB84169C2D08FD5161B6868FFC133E
0A759F056B87161F2D08FC516FB6858F
8D147B0A669E05D28916A22C08FD5175
B6858F0114BA0A859C05AC8C162A2C08
FE5160B6878F63147C0A1B9A05F38F16
C22B08FE514FB6818F1E13620A2C9705
4C93167D2B08FE5142B6838F6213780A
8C93051FA0166B2B08FE513CB68A8F02
146A0AAC8C0547A2168A2B08FE512AB6
7B8F58146A0ACB850576A116D82B08FE
5130B6848F17147D0B618305619E163C
2C08FD513AB6838F7913600A0F8405E9
9A16B02C08FD5151B6828FE5135D0A7E
8505E19216282D08FC5180B6848FED13
420AD38905BB8D16932D08FC519AB681
8F2113480A908F05918B16F92D08FB51
C0B6828FCD12600A2894050683164A2E
08FA51D0B6828F1C14530AB799054580
168D2E08FB51D9B6858F8913200A829E
05F97F16C62E08FB51D7B6858FDD131D
0BB2A105FF7E16EC2E08FB51C8B6808F
05134F0AD3A305CC7C16052F08FB51BE
B6838FF8123B0AC2A5054D7E160A2F08
FA51B1B6848FD413310A4FA6059E8016
F92E08FA51A3B6818FBD14660A75A505
A58016D12E08FA5188B6848FD814660D
A2A4052782168C2E08FA5193B6848F42
14640A8AA3050284162A2E08FB518EB6
7F8F34154F0A08A205738416B62D08FB
518BB6838FCC13720AD4A0050E871639
2D08FC5181B6838FA9133D0A149F0595
8A16CB2C08FD516DB67D8FC414430A95
9C050C8D16752C08FE5166B67B8FCE13
200AFD99059D8C163D2C08FD514FB67F
8F8B16650A219805A89016252C08FE51
43B67D8F6914AF0A8E9505BC9716262C
08FE513FB6798FC614810A889105EC92
16372C08FE513DB6818F0714400AC58F
056F9216542C08FE5157B6858F2C1429
0AF28F05A99C167B2C08FF5171B67F8F
0F14B00A2D8C057CA016A12C08FF5182
B67D8FFE13870A61870572A016C62C08
FF51B2B67D8F0A13350A818405E1A116
EA2C080052C6B67A8F1413E10A898205
27A2160C2D080052DCB67D8F1F137C0A
5481053DA1162D2D080152F3B6798F3A
139D0A1D81050BA1164F2D080052FBB6
7F8F0E14420A338105EBA016792D0800
52F4B67D8F6415550A6A8105F89D16AD
2D08FF51E7B6818F6616450ADC82058F
9716E12D08FF51F2B67C8FDC15FC0A90
8605328E16132E08FF51EEB67F8F7A13
760A398D057185163D2E08FF51FBB67C
8F38179A0A1595058B84165B2E08FF51
F4B67B8FFF14140A889A05B782166F2E
08FF51E3B67C8F7A13730AFA9D05ED85
167A2E08FF51DDB67E8F44139D0AC79E
05F485167B2E08FE51ABB67C8FC41369
0A8C9E056C86167A2E08FE51B2B67A8F
A913760A509E05328716792E08FE519A
B67A8F9513440ADD9D05698616762E08
FF518AB67D8F0115980AC59D05038616
6B2E08FE5177B67C8F0914470AE49D05
EA8716572E08FE5164B67D8F01141B0A
339D05DF85162F2E08FD5149B67A8F55
13340A809D05218416F02D08FD5121B6
808F8F14060A8D9E05DF8516992D08FD
510AB67D8F5514670A719E051E8A162A
2D08FE51F8B5788FEA131C0A669C05C0
8F16B42C08FE51F5B57A8FAA13620A6D
98051495163F2C08FE51EEB5818F2413
910A8C93059A9816D82B08FE51F6B57E
8F9F14350A328F05509916972B08FD51
FDB57A8FB8144C0A228C05D39F16842B
08FD51FFB5778F07145E0AD88705C1A4
169C2B08FD5111B67A8FBA13190A1A83
05AFA316DD2B08FD512BB67F8F96132A
0AAE8005C7A216362C08FD515AB6768F
FB13980CC17F055EA516A42C08FC516F
B6808F9C137C0AA47E0511A5161D2D08
FC519CB67A8FE714C40A327E05089816
8E2D08FC51B6B6768F5A14980A7C8205
509716EB2D08FC51C1B6788F2B150D0A
C28605AB9716372E08FD51C8B6758F8E
138D0AFE8905368916702E08FD51C2B6
768FC113B00A8F9005008F169C2E08FD
51B1B67F8FB1134C0A5C9305568E16B8
2E08FD518AB6758FE615AA0A6D940588
8A16C92E08FD516FB67B8FC114580A0B
9605E18E16CB2E08FD5157B6818F4F16
FB09EF9505FF8C16BD2E08FD5151B677
8F9814C50A0A9605A88C16A22E08FE51
39B67C8F8B135C0A6F9605BD8F167C2E
08FE5146B67A8F8D139A0A659505A38E
164D2E08FE5137B67C8F33146F0A0D95
05FA8B161D2E08FF5148B67B8F9F1318
0A569605798916EC2D0800524CB67E8F
0B14550A2F9805B08716B62D0800525E
B6708FCF14950A279A051B87167B2D08
00527CB6768F2915640A769B05D18816
372D08015284B67E8FF213640A7C9B05
A98916EA2C0800529EB67A8FA1142D0A
DB9A055C8C16962C080052ADB6788FF6
139C0A319905889116442C080052A5B6
7B8F2613FB09FB9505F49516F32B0800
529EB67F8F0614340A2592056D9716B1
2B080052A5B6738F2C133C0ACC8E05BC
9B16812B080052B0B67A8F3713C60A57
8B05C89D166A2B080052BFB6768FFB13
590A188805F99F16702B080152B3B676
8F2414940A9D85058CA2169F2B080052
BCB67A8F8A13A20ADE8205EDA316002C
080052BFB6748FD913280A468005B4A0
16862C080052D8B6758FEE13890AA97F
0596AD16242D080052CCB67A8FE41344
0A8E7B057CB016E32D080052C6B6748F
0414530ACF760512AB16B32E08FF51C9
B6768F8814670A17760598AC166C2F08
FF51CCB67A8F1614900AC0750569AE16
0A3008FF51D2B6768F7F13320AA47405
B2A616813008FF51E3B6738F4D17D609
5B78055C7F16D03008FF51DFB67F8F4A
154F0A0E8905A58616F730080052DCB6
7D8FF9142E0A079405289516FA300800
52E7B6818F85149C0A5B9305D39516D4
30080152C4B67A8FB814870AC8900509
97169B30080152A2B67F8F5A14B30AA1
8E05099616583008015286B67A8F2014
930A078E05BB921614300802526FB678
8F8F14970A398F05B19216DB2F080252
5EB6778F32157F0A2590052A8D16AE2F
08025257B6778F4B15380ADB9205C889
168E2F0802525EB6818F2615440AAA96
05B97E167F2F08025260B67A8FFB1475
0A3F9D05CA7716832F0802526BB6818F
EB148D0AD6A405487416992F08035255
B67A8FE214850AE4AA052D7116C82F08
035248B67A8FE6144A0AB7AF05786F16
153008035237B6818F9414920A46B305
846E167F300804520EB6788F7414690A
9CB505A16D16FA30080452FDB57D8F67
167D0A2AB705466D168931080352E5B5
7A8F57155E0A3DB805506C1630320803
52CCB57F8FE514550A2EB905C76B16EE
32080352BFB57D8F0B154B0A2EBA0574
6716C033080352C6B57F8F2C16920A5F
BC05FD6516A434080352D0B5858FD215
7E0AC2BE054865169035080352D6B57D
8FB8154D0AE6C005A165168036080352
EEB57E8F4816800A84C2058363165E37
08035216B6838F1D16600A9EC405245F
16283808035226B6858F06166C0A3AC8
05B25816CD380803523AB67D8FE018A9
0A06CF051D531649390802524BB6778F
2E16550A5ED705DF5016A0390803525E
B67D8FC215510AA2DD05AC5016C83908
03526FB67D8FC117540A16E105855216
C73908035284B6778F46163C0A72E105
CB5A169D3908035291B6788F2216F60A
7BDC05A55E165739080452B1B67D8F29
16A90A41D6059D5E160539080452B4B6
7B8F7A155D0A71D205DA5F16B7380804
52C5B67F8F1D16940ABACF053660167E
38080452DFB6798FF6159D0AD3CD0525
6116633808055201B7828F8C16590A48
CC05965F1674380805521BB7828F3B15
A90AB4CC050D5616B23808055243B785
8F6A15170ABBD2058C52162139080552
77B7838FA916240AB1D905005016BC39
08055296B77C8F2617E109FBDE053F4E
16863A080552B4B7838FA617360AFCE2
050F4A16683B080552C8B7768F6F17BA
0AA9E705404016603C080652C8B7818F
E8188A0A11EF05EB36165B3D080552BF
B76B8F4A19460AA8F805FC2B164B3E08
0552B3B75F8F2C1A1D0A350406361B16
2A3F08065299B7598F931C9E0A081206
4B1216EB3F08055281B7578F441C620A
101F06F2FD15834008055253B74D8F4E
1BAC0A502E06B4E715F8400805523CB7
4B8FE91A840A82400637DF154F410805
5246B7428FC61A410AF34F066ADF158C
410805523BB73E8F161C7C0ACA58060C
DE15AE410805522DB73E8FD41B530A26
5D06DCE115C44108055217B73C8FFE1B
4B0AB65D06D4EB15D9410805521FB73C
8FEE1C630A45590612EF15FE41080552
F2B63C8FA81D670AA25406AAE9154142
080552C9B6378FB71FD70AC3540641D3
159F42080652B2B63A8F3A1D730A105E
061BBB151C43080552B8B6318F1F1CEB
09DC6E068EAD15B543080652B5B62C8F
CF1A760A7E7F0610A5156044080652C8
B6238FF019670A728D066C9D150C4508
0652D8B6208FAC1A780ADF9806E09415
B345080652D2B6198F601B900A61A306
DB91155846080752BAB6178FF11D240A
66AB06968D15E946080752A2B6098FB5
1D910A07B206A5881562470807528BB6
008FFD1EDF0958B806778715CC470807
528DB6FB8EF81D540AABBC0630871523
4808075283B6F78E9E1DC30AF9BE0606
8715664808085282B6F58EBF24730A32
C0061D87159E480808526DB6F18E4A1C
F409A2C0065B8715D7480809525FB6EC
8EBD1DFD0A9BC0062487151449080952
6DB6F48E971F490A87C0067B86155F49
0809525FB6EE8E1F1D310ABFC0065A85
15B8490808527AB6F38EE51D710A57C1
06C88415274A08095271B6E98E14253F
0A12C206988315AB4A0809525BB6EF8E
9424200A0EC306398215384B0808523E
B6EC8E1C242A0A73C406148215D64B08
095228B6E78E74230C0A93C5069C8215
844C08085207B6E48E2228BB0A07C606
C48215384D08095208B6E48E0027910A
54C6067A7E15EF4D080952F8B5E68E7C
233B0BA1C806F87615A44E080852E0B5
DD8E9525830AECCD06CC7215514F0808
52BBB5CE8E4E24E30996D306E67015F3
4F080952BCB5CC8EDB220C0A20D80698
6D158850080852A8B5C58EFB1EFF0970
DC06976A15185108085284B5C78E571F
460ACBE006296A159A5108085257B5C0
8EB81F7B0AA6E306156A151652080852
40B5BF8E8523170A2EE5069C69158E52
08085202B5BD8E131ED60909E606B069
150153080852D2B4B98E49214D0A7AE6
0638691573530809529AB4B58E452274
0AE6E606086915E05308095260B4B98E
3025B90A39E706E9681547540809523A
B4BA8E371E1A0A71E7068D6815AB5408
095200B4BC8E0F1A9E0AADE7069B6815
0555080952C2B3BA8EB51DFE09D2E706
C76815505508095271B3B48EDC2A7B0A
CDE7060569158F550809523EB3B78EF3
20320AA3E706FD6815BF55080A5204B3
B68E47205F0A75E7060F6915E555080A
52C2B2BB8E6A1B8D0A49E70665691503
56080A528FB2BA8E541A850A07E70662
69152356080A5257B2BB8E7120000AD1
E6062069154956080A522DB2B98EE01E
A40AD1E606D968158256080A52FDB1BF
8E8A1B440AF1E606536815DA56080A52
DEB1B88EF1242A0A37E7062568154657
080A52B7B1B38E3E286F0A7BE7061568
15DD57080B5294B1BB8EA6202F0AA6E7
061F68159258080B527DB1B88E45203B
0AB4E7061F68156659080B5259B1B78E
D41D720AB8E706966715445A080B5233
B1B58EF71D250AF1E706386715285B08
0B521CB1BD8EB61F850A41E806286715
0A5C080B52EEB0B78EBD1E1B0A7CE806
3E6715DC5C080B52CCB0BD8E5C20030A
98E806216715975D080B52B3B0B88EBC
1C0F0AAEE8062F67153B5E080A5296B0
B48EE41F2F0AB9E8062E6715C15E080B
5277B0B68E511DE109BFE80617671529
5F080B5260B0B48E9821420ACEE806F6
6615705F080B5259B0B38E1920000BE6
E806106715965F080B5238B0B68E881E
F80AE6E806556715A45F080B5220B0AC
8E771E240ABEE8069367159A5F080B52
17B0B28E08209A0A82E806F26715895F
080B5209B0B88E2720110A1EE806F668
15745F080B52EEAFB18E1126550A66E7
06D56815645F080B52CCAFAE8E231E30
0AE6E6066B6815665F080C52AAAFAE8E
13247F0ADBE606E867157F5F080C527F
AFAF8E041E3C0A25E7062F6715B15F08
0C526AAFB08E241D270AABE706C26615
0560080C5245AFB18E441F350A33E806
D666157560080C522DAFAB8E861E7E0A
84E806C866150061080B521CAFB08E43
1E330AB0E8061F66159B61080B520DAF
B68E991B030A02E9065066154162080B
520AAFAF8EEC1F660A3CE906716615EA
62080A52F6AEAC8EC71FAD0933E906D2
66159663080A5200AFB18E6419B80A02
E9069166153E64080A52F7AEB28E0A1E
5E0AF3E8069B6615D964080A52EAAEAF
8EFF23280AFCE8062466156F65080A52
E4AEAF8E791E260A2BE906F26515F865
080A52E8AEAA8E1D222B0A70E906FA65
157266080952EEAEAC8E1C1DD60995E9
06ED6515E266080952E3AEAE8E091D79
0AAFE906E565154467080952F2AEAC8E
9620480AC1E9063F66159E67080952E6
AEAD8E6E244D0A99E9064A6615F16708
0952DBAEAC8EE72A250A74E906966415
4368080952C6AEAC8E4021950960E906
4966159568080852C4AEAA8ED61E690A
55E906296615EC68080952B6AEAF8EE9
1A7D0A57E9061266154969080A52A0AE
AC8E06210A0B65E906096615AA69080A
52A8AEAB8E0935020A73E906FA65150E
6A080A52A1AEAC8E7A4A480A81E906FA
6515746A08095293AEAA8E5D24390A8A
E906E86515D66A08095292AEAA8E641E
0A0A98E906CA65152E6B0809527EAEA5
8EBC20680AB1E906A46515856B080952
71AEA88E1634370AD5E9066E6515DA6B
0809526FAEAB8ED43EC20A07EA066465
152F6C0809525EAEA38E954D300A31EA
061865158C6C08095250AEA48EBB3330
0A67EA06FD6415F16C08095249AEA38E
2A2C240BA4EA06FE64155F6D0809523B
AEA18EEF26200AC0EA06116515D76D08
095242AEA78E3321490AC0EA06116515
596E08095235AEA38EAA1E440AC6EA06
116515D76E08095228AEA88EF12B990A
CEEA061165154D6F0808522EAEAA8E71
28190AE1EA06FA6415BE6F0808520EAE
A38ECA22220BF2EA06F3641520700808
521CAEA08EC3222A0AFAEA06F9641572
700808521AAEA28E43356B0A02EB06FE
6415B97008085202AEA38EB7274D0AFF
EA06296515FC7008095215AEA78EDB21
7A0AF0EA06E764154171080952FEADA7
8E8224390A08EB06AE64158E71080852
1AAE9F8ED720680A4FEB069A6415E671
08085215AEA58E202A6D0A94EB069C64
15567208085216AE9A8E49206C0AC3EB
06556415DF72080952FBADA28EE81F4C
0A07EC061464158073080952FEAD9F8E
521E3C0A5BEC06D663153874080952E8
AD9A8E141F390AC2EC06056315FF7408
0952D9AD9D8E881B870A97ED06936115
CF75080852D4AD998EA5185E0A0DEF06
5661159476080852C8AD958E071CB00A
4DF006DE60155377080852C9AD908EAB
198B0A4FF106306015FB77080852C7AD
928E901B380A43F206D45F1585780807
52CCAD908E201A6F0A45F3067A5E15EE
78080752CEAD8B8EAB1B1F0AA6F40602
5E153279080752D4AD878E0E1F4A0AD9
F506F85D155579080652E0AD838EA91C
5D0A89F606C55E155E79080652D9AD87
8E621A600A65F606005F155379080652
D6AD838E1D24310A0BF606A75E154379
080652D6AD828EF91E470AFDF506135F
153679080552DBAD868E30302D0AD0F5
06C95E153D79080552D2AD7D8ED3305B
0AD1F5062F5E155B79080552C7AD818E
9620690A43F606325D159D79080552BF
AD778E8D1D5A0A0DF706285D15FB7908
0452BCAD788EA31C410AACF7069D5C15
7A7A080452B5AD768E54174D0A62F806
985915107B080552A2AD748E7C14ED09
66FA06A65815B77B08045291AD758EE3
18800A80FC068C57156E7C08045282AD
6D8EA215420A54FE064456152A7D0804
5257AD698E7E13840A140007825515ED
7D0804522EAD678E8E144E0A9201075F
5415AA7E08035210AD5B8EB812630A09
03075B5215677F080352F0AC678EC315
DD091F05075B49152280080352E0AC56
8EB610310A8D0B077D3E15DD80080352
C7AC448E4F10150ABA16078C38158F81
080352B1AC3A8EB111130A5122073132
153582080352ADAC268E920F220A672D
071E3015D28208025293AC1A8EBD0FF4
0BCE35074A2B15598308025266AC078E
8A0F480A3A3D07042815C9830802523D
ACF58D4410450A0D44076E2715218408
025212ACEE8D8B107F0A8048073E2715
6084080252ECABE38DF90F000ABE4A07
B727158A84080152C1ABE38D81100E0A
8B4B075E28159F8408015291ABDB8D73
104E0A644B073A2815A88408015249AB
D18D7D110B0A2A4B07C12715AF840801
521DABD28D3611390A424B07882715B8
84080152DFAAC98D2C12240A784B072E
2715CD84080052C4AACD8D01136B0AD1
4B07932615F08408005270AAC88DCE10
720A584C07252615278508005202AACA
8D1710F909E54C07B025156E85080052
B0A9C78DBB0F560A754D07412515CE85
0800524DA9C38D5B0F4D0A064E07C624
154486080052F2A8C38D640F760AA94E
07DF2315D586080052B4A8B88D830F1D
0A8D4F076123157D8708005265A8B88D
020F460A7F5007EE2215408808FF511C
A8BA8D9D0E330A4E51071F2215168908
FF51D0A7B58D8A0E1C0A4B5207D42015
058A08FF5184A7B08DA3100C0BDA5307
791C15F98A08FE5146A7A48DAE0E4B0A
755707EC1A15F48B08FE51F3A6AA8D52
0E670A345B07591A15EF8C08FD51C6A6
A08DC00E460AC25D07DA1915D28D08FD
5180A69F8D2F0E570A635F073B19159F
8E08FD5141A6928D6710200ACB600718
1615488F08FE5100A6908D010F2A0ABE
63073C1315CE8F08FE51BFA58A8D230F
1B0AE767077412152F9008FE519FA58C
8D8B10350A1C6B07641215689008FE51
5EA5838D120FED09F76C077812157D90
08FD512DA5808D31100B0BA06D07FD14
15719008FE51EEA4858DCF0E290A476C
07F31615519008FE51C4A47C8D3F0F7E
0AC769075B18152C9008FE5192A4788D
2B0F470A5A6707CC17150E9008FD5157
A47B8DE211320A056607761815FF8F08
FD5139A47E8DA90F000A0465073D1815
0C9008FD5101A4788D7D10460A806407
6D1615399008FD51CEA37F8D9E0FF709
846507B712158B9008FD519CA37C8D7D
0E240AA96807251115FA9008FD515BA3
7C8D560F750A156C07DC0F158A9108FC
5128A37F8D000F390A0F6F07780F152D
9208FC51F7A2798D720E2A0A2E710704
0F15DE9208FC51BDA2718D500EEA09E2
7207760E159B9308FB5188A26C8DE10F
400A857407400E15579408FB5161A26B
8D4410C90ABF7507150E15159508FB51
1DA26E8D45100C0A8F7607E70D15CD95
08FA51ECA15F8D3C0EBE0A1D7707C90D
157E9608FA51B1A1638D500E3F0A8077
07CC0D152C9708F95177A1628D0C1026
0AB37707D30D15D19708F95164A15F8D
710F380AC07707830D156D9808F85137
A1608DC40E040AF67707300D15089908
F85108A15A8D810E690A5A78074B0D15
9D9908F851E8A05E8D790E120A8F7807
730D15309A08F751CEA0618DC80F5C0A
887807500D15C19A08F751AFA0548DDA
0E580A877807550D154E9B08F75196A0
5B8D630E0B0A8A78072A0D15D49B08F7
5182A05A8D450E410AA27807160D1550
9C08F6515EA0588DDA0E050AC678071C
0D15BA9C08F55144A05C8D0D0F060AD6
7807340D15119D08F55128A0598D1A0F
060ACE7807230D15509D08F551FF9F55
8D810F9A0AD47807300D15789D08F551
EB9F608D790F170AD27807730D158E9D
08F551D79F558DFA0E020AB07807940D
159A9D08F551B09F598DA00F240A7F78
07550D15A49D08F5518D9F628DC50F82
0A7078076F0D15B89D08F551709F558D
C00F380A6678075F0D15DD9D08F45144
9F5A8DCA0E4D0A707807FF0C151E9E08
F4512F9F578D730F850AB67807A50C15
7B9E08F4510E9F578DC20ED5091B7907
810C15F49E08F351FE9E518D630E570A
777907160C158B9F08F351DD9E568D45
0E9A0AEF7907E10B1537A008F251CD9E
4F8D340E260A6A7A07B60B15F0A008F3
51B39E508DEF0DD409DE7A072E0B15B3
A108F251A09E548D580E6C0A917B07AE
0A1577A208F251969E538DAE0E130A6B
7C07570A1532A308F2518F9E4E8DEF0E
040A467D07D60915ECA308F1517E9E49
8DBD0E3C0A2F7E07B109158EA408F151
769E4D8DB50E680AF17E075B091522A5
08F051679E4B8DC310830AA17F074409
15A5A508EF515E9E4C8DCD0E400A1D80
070C09151AA608EF51509E448DE61196
0A8580073709157DA608EE51439E428D
410F6D0AB78007FB0815D0A608EE5131
9E3E8DD70E250AE88007F1081519A708
EE51259E418DE10F2A0A108107E70815
5DA708EE511A9E468DE610130A2A8107
B608159EA708EE51099E3E8D6E143F0A
6881074C0815E2A708EE51FE9D468D1F
15600AE4810717081524A808ED51E39D
428D8215C70A648207EF07156CA808ED
51E29D3E8DE511280ACE82076E0715BE
A808ED51C69D3F8D7112010A8C830751
061514A908ED51AF9D3C8D140F710A09
850795051574A908ED51869D398D0C0F
6F0AA78607CB0415DFA908ED51A49D2F
8D130F4D0A54880712041552AA08EC51
4E9D368DD20E8F0A048A07B80315CEAA
08EC51569D318DD10E2C0A698B075903
1555AB08EB514E9D2A8D350F2E0A868C
07160315E2AB08EB515D9D248DDE10F2
096B8D07A602157EAC08EB510D9D278D
C20E1C0A5F8E077B02151AAD08EA5109
9D238DA20E980A238F076B0215B7AD08
E951F89C258D240E600A968F07610215
4FAE08E851DD9C1B8D3E0E500AD38F07
610215E7AE08E851D29C1F8DBC0F7E0A
FA8F072C021575AF08E851C09C208DD2
0F490A499007C90115F4AF08E751AC9C
148DB10E190AE7900776011569B008E7
519F9C198D240E0E0AA79107BF0115CC
B008E751789C198DBB0DCE09F6910716
011520B108E651659C178DEB0D640AB4
9207A3001567B108E551589C168DAB0D
510ABF93076E00159BB108E5513A9C13
8D350E520AA39407640015CCB108E551
2F9C138DD20E260A4F9507330015F9B1
08E551179C128D250F8B0ACD95073C00
1520B208E551FF9B168D510E3E0A1E96
0757001541B208E451F39B148D810E45
0A3796079F001546B208E551DF9B0E8D
AE0E890A079607CA00153CB208E451C3
9B0C8DE20E200AC295078F001516B208
E551A29B0E8D810E550AAD9507BA0015
08B208E451929B0D8DE90F4F0A999507
960015FAB108E4516F9B0D8D560E430A
8F9507C40015F7B108E351659B048DEB
0D7B0A729507BD001502B208E351459B
0D8DE20D500A5C9507C4001513B208E2
51209B0E8D290EE10968950740001535
B208E251139B098D4D0E220ADD9507F7
FF1463B208E251F99A038D8D10170A70
9607EAFF149AB208E251E19A088D5B0F
FF09DA96079BFF14DBB208E151DB9A0C
8D9D0E410A51970752FF141BB308E051
C99A088D200E5C0AE0970745FF1459B3
08E051B29A078D4B13070A4C980721FF
1498B308E051AD9A0B8DB8101C0AA998
071DFF14C9B308E0518E9A088D680F65
0AE5980738FF14ECB308E0517A9AFD8C
9F0E460AF198075CFF14FFB308DF5159
9A028DC00E9E0ADA9807D3FF14F5B308
DE514E9A058D990EF6098F9807E3FF14
D6B308DE51419A038D100E550A3F9807
E3FF149CB308DD51379A068DA90EE70A
1998071200154DB308DD512E9AFB8C1C
0F150AF69707040015EFB208DD51109A
FF8C290E8D0ADB97073300158EB208DC
51089A048D480E390AB797075000152D
B208DC51F599FF8C0F126B0A8D970736
0015DAB108DC51D499048D7B0E340A74
970708001599B108DB51DA99FD8C770E
780A7D9707DDFF1470B108DC51D29900
8DEB0E7E0A909707D6FF1462B108DB51
D199038DF10F7C0A9E9707E7FF1472B1
08DB51D099018D820F620A8B97070400
159AB108DA51BE99FA8C3D0F210A2897
07A8FF14D6B108D951AB99FF8CC30E70
0AEA960797FF141BB208D851A699018D
B10DFF09E296078AFF146BB208D85194
99018DD30EB90AED960791FF14B7B208
D7518E99048D340F690AFD96073EFF14
07B308D8518A99038D4B0E090A589707
59FF1450B308D7518099FF8C6E0F3E0A
A0970734FF148CB308D7516699FF8CA2
0EC809DF970724FF14C5B308D6517D99
048DC20ECD09289807E5FE14EEB308D6
514E99FB8CE90E580A9A9807E8FE140B
B408D6516799048D6E0E3C0AE898072E
FF141DB408D5514C99FA8C050E520AD7
9807ABFF1422B408D5515699008DD70D
480A649807D9FF1419B408D451499901
8D5B0EA20AF49707D6FF1402B408D451
4399FE8CCD0D9C0BB59707E0FF14E2B3
08D4513899018D000E390A8F9707D3FF
14B5B308D4514899F58C030E6C0A8197
07E7FF1482B308D4515099008D380E5A
0A779707F7FF1446B308D4514D99F78C
980D320A6B9707FAFF1407B308D3513F
99FD8CDD0D3D0A5A9707FEFF14CFB208
D3514199018D9D0E0A0A4D97071B0015
9AB208D3514E99F88CA20E110A319707
04001573B208D2514A99FB8C770D320A
189707F1FF1455B208D1515699FF8C5B
0F580AEE9607FEFF143FB208D1514D99
008D06115E0AB1960725001536B208D1
514B990A8DE610200A4596074D001534
B208D1515A99048D0B10E809AE95076E
00153BB208D1514A99FF8C5C0E100A21
95077B001549B208D1515199048D970E
260AC4940788001562B208D0514799FF
8CF90F3A0A81940788001581B208CF51
5599008D9A0F1D0A499407780015A9B2
08CF515599008D6C0E5C0A4394071500
15D5B208CE513E99098D430E5809AC94
07C2FF1403B308CD513D99FE8CB60D69
0A57950791FF1435B308CD513D99008D
A80DDB0907960769FF1461B308CD5142
99FE8C480F4E0A94960791FF1485B308
CD514E99FA8C4B0E3E0ABF9607AEFF14
A2B308CD514599FD8C160F460AB19607
E3FF14B4B308CD514F99FD8C3C0E420A
8D9607FAFF14BEB308CD515799058D87
11050A679607010015BEB308CC515099
008D440F350A589607010015B9B308CC
514D99018DF00E4B0A519607F7FF14B1
B308CB514999F98C520E4E0A549607F4
FF14AEB308CB515F99F88CD713FD095E
9607F1FF14A9B308CA516C99FD8CE50F
1F0A6A9607B8FF14AAB308CA516999FB
8C800F350A9A96079EFF14ACB308C951
6199FA8CD40F310ADF960791FF14B3B3
08C8516999F88C5C0E010A1897077AFF
14B8B308C8514899F98CC30F390A4E97
0780FF14B7B308C8514C99018DCA0E1B
0A7197079BFF14B0B308C8514D99FD8C
6A0E830A7B97077AFF149EB308C7514C
99F98C170E4D0A8D970797FF147DB308
C6515199FD8C190E7B0A929707A1FF14
53B308C5515299F68C5C0E440A919707
EDFF141EB308C5514399F38C470E4D0A
6397070E0015E7B208C4513D99FA8CD8
0D3E0A2E9707150015AFB208C4513B99
FA8CED0E370A1297070800157EB208C4
514199F68C310E410A0097070100155B
B208C4513099F78CDF0DBD0ADE9607EA
FF1447B208C4513699F98CEB0D5E0AD0
96079BFF1447B208C4512999F88CC411
060AF89607A5FF1459B208C4513499FE
8CFA0E350A23970748FF147BB208C351
3299EE8CCC0D870A71970734FF14B6B2
08C3513399FD8C120E2D0AC4970713FF
14FCB208C3513A99F78C560FDA090998
07F2FE1450B308C2513D99F98CDD0E07
0A479807EFFE14A8B308C1513D99F18C
820E2F0A6E9807D1FE14FCB308C1513F
99F38C1E0E500AA89807ADFE1444B408
C2514999F48C770D670AF69807B7FE14
7AB408C1514699F58C940D280A1A9907
BAFE149AB408C1515199F38C700E4E0A
269907C7FE14A4B408BF515D99FD8C51
0E5B0A24990703FF1494B408BF515599
F68CCA0D200A01990731FF146DB408BF
515299F08C200E6D0ACE980759FF1431
B408BD514F99F78CC90D460A9398077A
FF14E5B308BD514299FA8C5F0E390A58
9807A5FF1494B308BD513B99EF8C210E
600A1C980797FF1446B308BC513D99F2
8CDD0D0B0AF7970787FF1401B308BC51
3499F18C790E2A0AE7970776FF14CDB2
08BC511C99F78CA60FAB0AE597077AFF
14A9B208BC511399F08C0611970AEC97
0752FF1496B208BC511B99F08C07102D
0AF9970731FF1495B208BD510E99F88C
670E610A12980710FF149FB208BC5110
99F58CDB0E7C0A3598071DFF14AFB208
BC510499F08C0C0F760A3F980721FF14
C4B208BD51F698F18CB00E480A469807
24FF14D6B208BD51F198F48C8A0E020A
4398071AFF14E5B208BE51F198EC8C39
0F920A43980731FF14EFB208BD51E798
F58CBD1B120A3C98073BFF14FFB208BD
51DE98F18C1E11370A2C98073BFF1411
B308BC51E198F28C5A0ECA092098073E
FF142AB308BC51DC98F28C000E230A18
98073EFF144FB308BC51C698F28C400E
6A0A10980734FF1484B308BC51D498F7
8C9511380A14980717FF14CBB308BB51
C398F08C210F520A239807FCFE141CB4
08BB51C798F48C020E5F0A419807F9FE
147AB408BA51C198F48C1E0E4A0A5A98
078FFE14D2B408B951B798F58CAD0E31
0AC098077CFE1421B508B951BB98F08C
81313D0A32990782FE1457B508B951B1
98F48C641C310A72990785FE1472B508
B751B198EE8C3710310A869907BEFE14
6DB508B651B698F08C3710400A6F9907
E8FE1444B508B651BD98F08C6C0E800A
35990717FF14F8B408B451C898F08C89
0D3F0AF0980770FF148FB408B451D198
F78C8A0EC40999980773FF1411B408B4
51BA98F68C830D5E0A59980752FF1489
B308B551C398F18CB90E350A4398076C
FF14FFB208B451B698EF8C990E210A2E
98076CFF147AB208B451B698F08CBA0E
600A0E980773FF1407B208B351BF98EE
8C3C0E350AF1970784FF14A9B108B351
B198F58C4D0EF30AD297077AFF1467B1
08B351CA98F08C5F0E900ABF970763FF
144AB108B251CF98F28C2B106F0ABB97
0748FF144EB108B151DE98F88CC40E17
0AAD97073EFF1477B108B151DF98F48C
410E2D0A8A97073EFF14BCB108B051DE
98F28CE40D2D0A46970742FF141AB208
B051E398F28C7E0EF2091A970745FF14
8AB208AF51E098F98CE20D1C0A019707
48FF1405B308AE51E798F48C240E3F0A
03970710FF1484B308AE51F098ED8CB6
0E210A649707B0FE1400B408AD51FC98
ED8C2B0E460A0C9807BEFE146CB408AC
51F398F08C480F200AA09807AAFE14C4
B408AB51ED98ED8C810EDB09319907A6
FE1407B508AB51F098F08C45113F0A89
9907A6FE1431B508AA51F298F18CD30E
340AB59907AAFE1442B508AA51F898EE
8CAD0E310AC09907DBFE1443B508A951
E298F08CED0E240AAB9907F6FE1432B5
08A951E998F18C650D920A7B99072AFF
1411B508AA51D198F08C1D130C0A4499
072EFF14E8B408AA51D598F08CE90E1B
0A11990742FF14B4B408A951CF98E88C
AE0E590ADA980759FF1474B408A951C6
98E68C160E6D0AA8980770FF142EB408
A951CF98EE8CE60D640A79980769FF14
DCB308A951CD98EB8CBC0D150A4E9807
69FF1482B308A951CA98F18CAE0D7A0A
2E980787FF1423B308A851C998E78C85
0DFA090A98078DFF14C4B208A851DF98
F08C870D1A0AEA970791FF1468B208A8
51D498EE8CDE0D240ACA970784FF1417
B208A751D898F48CC50FFD09B4970787
FF14D9B108A651D398F48C820F3C0A9B
97077DFF14B2B108A651D798F18C920F
6F0A85970770FF14A7B108A551CE98F4
8C2C0E530A7897074FFF14BCB108A551
C798EF8CDF0D610A7697073BFF14F0B1
08A451D898F08C9F0D700A5897072EFF
1443B208A351E098F18CB90D510A3597
0738FF14B5B208A251E098F28CE10D2F
0A1B970738FF1435B308A351E998F38C
620F390A189707EFFE14BDB308A251E2
98F48C4710450A799707D8FE1444B408
A251E998F58CFB0D6F0AE69707D8FE14
BCB408A151F698ED8CF10DD009349807
BEFE141BB508A151F498E88C400E6B0A
9E9807A3FE1460B508A151E498DF8CE5
0D350A209907B4FE1482B508A051E498
E08CE40D0C0A589907C1FE147EB508A1
51DC98E68CA10D480A56990709FF1455
B508A051DA98E68C880E850A0699073E
FF140CB508A051D398E98CF90D8C0A9B
980784FF14A6B408A051DE98E38CC30D
1D0A3098078DFF142EB4089E51D398E8
8C7E0D530ADF97079EFF14AFB3089E51
CC98EC8C330E170A9E97078AFF1432B3
089D51CD98E48CF30EEF0979970791FF
14C3B2089D51CF98ED8C4B0E6B0A5897
0784FF1468B2089D51D398EE8CF30DC5
094097077DFF1425B2089B51D398E58C
7D0E330A2897075FFF1401B2089A51C7
98E78C1D10170A1B970752FF14F7B108
9A51CD98EA8C390EEB0A1D97074BFF14
09B2089951D198EA8C140E430A1B9707
31FF142FB2089751D798F28C380E3D0A
1797072AFF146AB2089651E298EC8C75
0EF7091597072EFF14B7B2089551DC98
E98C370E3E0A19970724FF140CB30894
51E498E38C8F0DFD0924970734FF1468
B3089451ED98E78C790E2A0A25970734
FF14C1B3089451E798F48C430ED90921
970727FF1417B4089351FB98F28CD110
D60D279707F6FE1461B4089351F498EE
8C7E0F220A719707E8FE149CB4089351
F698EC8CD10E190AC59707E2FE14C3B4
0893510799F48C1C0F710A059807E5FE
14D1B40893510B99EA8C710F080A1F98
0721FF14C9B40893510399E68CD10D58
0A08980745FF14A9B40893510D99E68C
8D0D8B0AD1970763FF1476B408945109
99EA8C0D0E690AA0970766FF1437B408
93511A99EF8CDD0D290A8797079BFF14
F1B30893511899E98CEF0D550A5D9707
9BFF14ABB30893512999EE8C360E550A
329707A8FF1471B30894512199EC8C9D
0E420A1397078DFF1444B30895512299
ED8C430E9E0A0797077DFF1423B30894
513299EA8C4D0ECD090C970770FF1412
B30894512C99EE8C380F800A1D970766
FF140EB30893512499EA8C250F330A31
97073EFF1412B30893512299EC8CFF0F
8D0A5897072EFF141BB30893512C99F3
8CD10E110A7E970734FF142BB3089251
2A99F28C9E0E360A98970727FF1441B3
0892512A99F18C630F1D0AAB970727FF
1455B30891512599F28C7A101D0ABC97
0727FF146DB30891512399EA8C770EA3
0AC697072EFF1483B30891511C99E58C
5B0E8B0ACA97072AFF149BB3088F5128
99E78C220E440ACE970734FF14ACB308
8F511999F08CB20D760AC797073BFF14
B6B3088F511799E88CF80E5A0AB79707
4BFF14BAB3088F511899E88C160E620A
97970752FF14B5B3088E511399E78CF4
0D5C0A7297075FFF14ADB3088D510599
F08C5B0ECA0A51970770FF14A3B3088D
51FF98EA8C1C0E8B0A3797076CFF149D
B3088D51FB98EE8C550F410A22970766
FF149BB3088D510499E88C800E050A17
970763FF149FB3088D51FE98E68CE00E
7E0A1197075CFF14ADB3088C51F398EC
8C1C0FFA0913970763FF14C2B3088B51
F698EC8C3D0F860A10970769FF14D9B3
088B51ED98EE8CFE0E830A0A970769FF
14EFB3088A51F898ED8C420E210A0397
0773FF1402B4088951E998EC8C4C0F9C
0AF696078AFF1410B4088951F498F28C
680F030ADB96079BFF1416B4088951F7
98E88CC00F520ABC960791FF1415B408
8951F898F08C9D0E480AA796079BFF14
0FB4088951E998ED8C450E5D0A989607
91FF1404B4088951E598F08C120E680A
93960797FF14FCB3088951E998EC8C99
0D600A8E9607A5FF14F1B3088851D598
EE8C760E590A819607BCFF14E5B30888
51D598EE8C320F3B0A6E9607C2FF14D7
B3088751D398F08C240E9F0A5A9607D3
FF14C7B3088751C898F08C9C0E3E0A48
9607E3FF14AEB3088651CB98F08C1C0E
960A329607F4FF1497B3088551CC98F7
8CD70D5E0A1A96070B00157BB3088551
C498EC8C350ED10AFD95070B001560B3
088551BE98EC8C480E160AE795071B00
1545B3088351C998E88CBA0E710ACD95
0704001531B3088251CF98EA8CE90F83
0AC4950708001526B3088251CD98E68C
E90EFD09C59507DDFF1427B3088151D8
98F38C7E0E7F0ADB9507B8FF1434B308
8151EB98E88C940E890AFE9507AEFF14
4FB3088051DE98F38CA60E350A1A9607
9BFF1476B3087F51E898F08C420E240A
3496076CFF14A9B3087E51ED98EA8CE4
0E3E0A7696074FFF14E6B3087E51F998
F28CE40EE609C0960752FF1429B4087D
51F698E98C320E240AF196075CFF146C
B4087D51F098F48C210E0E0AFE960745
FF14A8B4087C51E998E78CCA0E6D0A1E
970745FF14D4B4087C51F898ED8C370E
7C0A3A97073BFF14EEB4087C51FA98EF
8C1A0E300A56970748FF14EFB4087C51
F698F58C570F580A5A97075FFF14D4B4
087C51FF98F18C270E6C0A57970763FF
149FB4087C51F698F18C310E1F0A5897
0794FF1456B4087C511699EC8CF40E5D
0A359707E3FF14FAB3087B511A99EB8C
5A0E6A0AEA9607D9FF1495B3087A511C
99EA8C850E0D0AB19607D6FF1432B308
79512399E78CF10D280A939607C6FF14
D8B20879512899E98C740E350A819607
CCFF148EB20879512999EE8C300F340A
759607D6FF1459B20878512999EC8C9E
0F0B0A609607C9FF1443B20878512A99
EB8C9D0E030A539607BCFF144BB20878
512899F48C970F3C0A599607ABFF1472
B20877512499ED8C3910910A61960776
FF14B5B20876511F99E58C220E870A89
96076CFF1413B30875512799EE8CBD0D
7F0AB396074FFF1483B30874511699F0
8C810D460AE7960721FF14FEB3087451
1F99EA8C9D0D7E0A3F970706FF1478B4
0874511999F48C580E420A9C97070DFF
14E7B40873511A99EC8C360E3A0AD997
0706FF1444B50872512699E58C6E0F94
0AFA970709FF1486B50871511F99E88C
4F118D0A0798070DFF14A9B508725126
99F08CF90E810A0B98070DFF14ABB508
71511F99EE8C7D0E4F0A09980724FF14
8FB50871512499EC8C900D420AFD9707
3BFF1457B50871512199EA8C2B0E5D0A
E197075CFF1406B50871512599E58C6F
0D410AB8970797FF14A4B40870511A99
E88CB70E430A7E9707BFFF1437B40870
510F99E98CC20EFC0A419707B2FF14C6
B30870510E99EA8C3B10FD091B97079B
FF1456B30870511799EF8C920E110A0D
9707A5FF14ECB2086F511899E78CC90D
670A02970794FF148DB20870511099E3
8C950D6F0AFE960791FF143BB2086F51
1C99EE8CFD0DFB09FF960780FF14F9B1
086F511999E98C970E4F0A03970780FF
14CFB1086E511B99EB8CB20E390A0397
0776FF14C1B1086F511A99EA8C890E35
0A0A970763FF14D0B1086F512999ED8C
0B0E220A1A970759FF1400B2086F5116
99E98C070E320A26970748FF1450B208
6E512899EE8CD60D2B0A2B97073EFF14
BAB2086D511E99E88CE40D2C0A279707
3BFF143BB3086C512599E88CD90D660A
2997073BFF14C6B3086B511F99F08CA9
0D630A2A970734FF1459B4086A512A99
E88C3E0E0A0A3497071DFF14E6B4086A
513199E88C470E670A5997071DFF1464
B50869513699F08C480E040A8D97071A
FF14D4B50869513399EE8CF60D650AA0
970717FF142EB60868513399EB8CE90D
480AAB970724FF146EB60867513399EA
8C750E2D0AA597071DFF148DB6086751
2B99ED8C570E570AAB970724FF148DB6
0866511C99F48CEF0D4A0AAC970748FF
1462B60865511499E88CE40E370A9B97
0766FF140DB60864510999EE8C0F0EF5
09799707A5FF1491B50864510599EB8C
920D670A439707B5FF14F3B4086351F9
98E38C900EC00A119707B5FF1439B408
6351FD98EE8C910EEE09EE96079BFF14
70B3086451F798F08CA20D510AE19607
94FF14A2B20864510499EF8C310D690A
E096079BFF14E1B1086351FE98EB8C71
0D570ADB96078DFF1436B10861510899
EC8C7B0D210AD8960787FF14B1B00860
510399E58C630E280AD9960776FF145D
B0086151F998E88C760DDF0ADA96075C
FF1442B0086051F898EE8CE80D460AE3
96074BFF1463B0085F51FA98EC8CC50D
3C0AF496074BFF14C3B0085F51FC98EE
8C080F080AFD960748FF1464B1085D51
F798F28C3E0E2A0A0697074BFF1429B2
085D51EE98ED8C0D0E030A0F970748FF
140FB3085D51EC98E88CB00D870A1B97
0742FF1400B4085D51E098F08C770D24
0A2997072EFF14E3B4085C51DF98E98C
650EE30954970727FF14ABB5085C51E1
98E38CB40D7C0A80970709FF1449B608
5C51D998EA8CB20D3C0AD09707DFFE14
B1B6085A51D298EA8CEF0D220A599807
C4FE14DFB6085A51E498E18CA60D640A
EF9807ECFE14D5B6085A51E098E78C9C
0D850A1099071CFF148EB6085A51E198
E88CDC0D5D0AC298074BFF141BB60859
51E598E98C930D4B0A5698077AFF1486
B5085951F298E18CF30D4B0AE997079E
FF14DDB4085951FB98F08C9E0DED0982
970791FF142AB4085851F998EB8CE10D
A90A3C970787FF1479B3085751F398E8
8C7F0EDD0916970787FF14D5B2085751
F398EC8C7F0D330AFF960791FF1445B2
085851ED98E78C730EA00AF296077AFF
14CEB1085751EB98EC8C1F0EA00BF396
0766FF1476B1085651E298EA8C9B0E41
0AFD960752FF1440B1085651E098EF8C
B70EE10908970752FF1429B1085451E3
98ED8CA20E680A12970745FF1436B108
5451D798EA8C0C0EF40C16970742FF14
5EB1085451E098EA8C7E0D070A0C9707
48FF14A8B1085351E098EF8C090E250A
FF960742FF1409B2085351DE98E48C9D
0D590AFA960745FF1483B2085251DE98
F28CBB0D800AF4960748FF140CB30852
51DC98E98CC50D140AEC960755FF149B
B3085251D598EA8C780D090ADF96074F
FF142CB4085151E098F08CC30D420AD9
960752FF14B4B4085151E998EE8CD60D
3E0ADD960727FF1429B5085151D398EE
8C120E8F0A279707F2FE1486B5085151
E998ED8C150E800AC09707D5FE14C4B5
084F51DE98EC8CE10E1D0A659807E8FE
14DDB5084E51E298EE8C800E1E0AA898
07F9FE14D3B5084E51E098EA8C9C0D6B
0AB3980748FF14A0B5084D51E498E48C
A10D0F0A51980776FF1452B5084E51F1
98E78CDB0D730AD497078DFF14EAB408
4D51F698ED8C0D0E310A79970791FF14
6FB4084D51F798E98CC80D010A3C9707
A1FF14EBB3084C51F698EC8C8D0DA20A
0B97079EFF1464B3084B510699EC8C1D
0E3B0AF0960794FF14DFB2084C510B99
E98CE80D870ADC960791FF1465B2084A
511099EE8CA30D420AD196078AFF14FA
B10849511D99EA8CBD0D410AC996078A
FF14A6B10849511399EE8C690E1A0AC3
960780FF146CB10848511A99F08CEA0D
FF09C2960763FF1452B10848511399EE
8C8B0E3E0AC5960763FF145CB1084751
1699EA8CD30E510AC696074FFF1483B1
0846511299EC8C430E7B0ACE960759FF
14CAB10846511299E98CA30D220AC996
0759FF142BB20845510F99EE8CCA0D3B
0AC2960759FF149BB20843510199EB8C
750E1D0AC596074BFF1413B308435102
99ED8C8E0E310AD496074FFF1487B308
4151FE98ED8C2F0E920ADB960752FF14
F5B30841511299EE8C680E5F0ADA9607
52FF1454B40842510099EA8CA80E720A
DD96074FFF14A2B40841510999ED8C72
0EA10AE1960755FF14DEB40840511D99
ED8C320E5E0AE0960752FF1407B50840
511D99F88C4D0E5C0AE2960752FF1421
B50840511D99F18C320E080AE4960766
FF142AB50840511D99F48C250F580AE0
960769FF1425B50840512099F18C5F0E
5B0AD996077AFF1414B5083F511B99F2
8CE20D760AD6960787FF14F3B4083F51
1D99EE8CEE0D710AC8960794FF14BFB4
083F511899F08C6D0E210AB596079EFF
1475B4083E512199EE8CD20D0E0A9F96
07AEFF1416B4083E512799EE8CBC0F97
0A8C9607B8FF14A6B3083D513899EA8C
1E0EBA0B7B9607B2FF142AB3083D513B
99F18C910F5F0A729607B2FF14ACB208
3D515099EE8CD70F310A6E9607AEFF14
38B2083C514A99ED8CB70E2E0A709607
A5FF14D8B1083A515F99E88C070E5F0A
72960797FF149AB10839514E99F28CC6
0E980A7A96077AFF1485B10839514A99
F08C4A0EF10A8C960766FF149AB10838
514399F28CBF0D620AA0960769FF14E1
B10838513F99EC8C600D350AAD960763
FF1457B20837513599EA8CBA0D330AB2
96075CFF14E5B20837513099F48C7A0D
0B0ABA960745FF148AB30836512C99EB
8CEF0D400AD796073BFF143DB4083651
3499F38CE20D400A00970738FF14E4B4
0836513999ED8C5712220A2397072EFF
146CB50836513299F08C4B0E280A4F97
0717FF14CFB50835513099EA8C5D0E12
0A9B970713FF1407B60835513399EE8C
05108E0AD7970713FF1408B60834513F
99F28C390EA30AEB970738FF14D5B508
33513399EA8C1C0F5F0ACD97075CFF14
6BB50834513499EC8CBC0D900A939707
80FF14D9B40834513399EA8C5C0D400A
59970794FF1425B40834512899F18C7B
0D760A22970794FF1462B30833512A99
E88C4F0E580AF696078DFF149FB20833
511B99EC8CE40D3E0ADB96078AFF14EA
B10832511899E68C820D460ACB960780
FF1452B10831511199EC8C390E1A0ACA
960773FF14EBB00830510A99E78C400F
2F0ACE96075CFF14BDB0082F510199F6
8C270EDF09D9960755FF14D2B0082F51
0B99EB8C7A0DFD09E796074FFF1423B1
082E510199F38C9C0D1E0AF5960742FF
14B3B1082E510D99EC8CA30D550A0597
073EFF1474B2082E510799F28C7C0F5F
0A0D97074BFF143FB3082D51F898F28C
4B0E480A1197074BFF1411B4082D5109
99F28C5A0DF90915970745FF14D3B408
2C510099F08C3D0E940A2497072EFF14
6CB5082B510B99F28C9C0F270A519707
09FF14DAB5082B510D99E58CAF0E3E0A
A797071AFF1413B6082A510999EB8C80
0F5C0AB597071DFF1412B60829511899
E68C6C0E1B0AC197072EFF14DAB50828
511099E78CDF0D600AC5970755FF1471
B50828511699F38C400E660A9997077A
FF14E4B40828511799EE8CA10D5F0A60
97078AFF1440B40827511299F48CCC0D
620A28970776FF1492B30827511499F0
8CA10D1B0A0A970784FF14E4B2082651
1299EE8CEC0D5C0AF096077AFF1440B2
0826511299F38CF10D570AE4960776FF
14B1B10825511799F28CD90D110AE196
0776FF143CB10823511D99F08C480E7C
0ADE960769FF14EDB00823511699EA8C
300F920AE3960752FF14C4B008225119
99EC8CCC0E940AEF960748FF14C4B008
22511199E88C8C0E800AFA96074FFF14
EEB00822510F99EB8C420E2E0AEE9607
59FF1440B10820511899EE8CED0D050A
D796075FFF14B3B10820510E99F28CA5
0D970AC3960755FF143AB20820511799
EE8C9A0D230AC9960742FF14CFB20820
511899EE8C9A0D070ADB960731FF1462
B3081F512799E98C240E820A1D9707E5
FE14EDB3081F511F99EC8C080E260AC5
9707DBFE146CB40820511D99EE8C150E
310A3D9807D1FE14D4B4081F512199EB
8CD70E510AAE9807BEFE1421B5081F51
1F99EC8CEE0E2D0A289907BAFE1452B5
081F511B99E58CDC0E6E0A729907D1FE
1462B5081E511299E78CB50EA60A7299
07F2FE1450B5081E510D99E98C9C0EB3
0A4199070DFF1425B5081E511A99E98C
780DD809FA980748FF14DDB4081D51FE
98E68CF70D530A99980776FF1482B408
1D510D99E98CF60D610A31980770FF14
14B4081D510D99EB8C500E240AF49707
63FF149FB3081D511A99EA8C2A0E390A
DE97075CFF1427B3081D511899EB8C93
0E7B0AD597074FFF14B1B2081C511E99
E58C330E410AD2970748FF1442B2081B
512199E88CC30D470ACE97074BFF14DF
B1081B512799ED8C0C0F250BC2970748
FF148AB10819511A99EC8CA50E2A0AA6
970748FF1448B10818511499EA8CDF0E
530A8997074FFF141DB10818510E99E5
8CD40EA80A6E970752FF1412B1081751
1299EC8CFE0E5C0A5097073BFF141FB1
0817510C99EE8CAC0EF1093B970752FF
144FB10817510499E98C450E300A2797
0748FF14A2B10816510B99E68C750E04
0A0A970742FF140EB20816511699EB8C
3E0E8A0A01970738FF148BB208165101
99EB8CC40D520A0F970734FF1414B308
15511499EA8CAE0D7B0A1B97073BFF14
9CB30814510999EE8CB90D100A189707
34FF141EB40812510D99E98CEC0D5E0A
21970721FF1492B40811510B99E88CF5
0D8E0A5F9707D1FE14EBB40811510699
EE8CA010610AF89707B7FE142CB50811
51FE98EA8CD60E870A969807B4FE1451
B5081051FC98EA8C0F0E570AF19807E5
FE1456B50810510F99EF8C600E6C0AE8
98071DFF143FB50810511199F08CA60D
A70A88980770FF1409B5080F511099E3
8CA80E790AF29707A5FF14BBB4080F51
0799E98CAC0D690A719707ABFF1458B4
080E510A99E88C9B0D180A209707A8FF
14E8B3080D511899EA8CB00D560AFA96
07A5FF1472B3080C511499EC8C060E70
0AE496079BFF14F8B2080D510799E58C
A80D570ADA960797FF1482B2080C51FC
98F08C350E690AD896079BFF1419B208
0A51F198EB8C740E570AD3960794FF14
BCB1080A51E998E78CC30E110AD09607
8DFF1475B1080A51E498EC8C300F920A
CF96077AFF1446B1080A51D398ED8CF6
0F5E0AD496075CFF142DB1080A51E398
E68C0D0FA30AE1960763FF1430B10809
51E098ED8CA60E1D0ADE960769FF144C
B1080751DE98E98C030F620AC9960773
FF1482B1080751DE98EE8C470EE409A2
960770FF14D0B1080751E898EA8C150F
3E0A86960780FF1432B2080651E898EB
8CB00EB20A70960787FF14A6B2080551
F198EC8C380E1E0A67960724FF142CB3
080551F598EF8CD70D350AD796071AFF
14BBB30804510199E98C7A0EDC0D5D97
072AFF144CB40803510399EF8CEC0D2E
0A92970706FF14D3B40802510599E88C
540D2F0AD39707B4FE1448B508025112
99E78C5C0E730A9E98078CFE149FB508
03511099E98CD20E6F0A7F990785FE14
CDB50801511899EF8C280E470A109A07
AAFE14CDB50801511699E78CCB0DB90A
369A0703FF14A1B50800511A99F18CAC
0D450AC3990763FF1445B508FF501899
EE8C800E5C0A0299075CFF14C5B408FF
501B99EF8CE40E0B0A92980766FF142A
B408FE501E99EE8C070E8E0A4098077D
FF1482B308FE500899E58CAC0D460ADC
970780FF14D9B208FC500D99E98CDD0D
280A8A970784FF143AB208FB500C99E8
8C630E060A5097078AFF14AEB108FB50
0599E98C060FE6091B97078AFF143FB1
08FA500899E98C220EEB0AF196077AFF
14F3B008FA501099EE8CC60E490AD996
0773FF14CDB008FA500099F08C710E27
0AC4960773FF14CDB008F950FD98EF8C
720E7A0AAC960766FF14ECB008F750E7
98ED8CCE0D6A0AA6960776FF1427B108
F650E198E38CFD0D580A8E96077AFF14
82B108F750D798E68C910F420A659607
69FF14F5B108F750D198EE8CCD0E6F0A
5C960752FF1479B208F750D198EB8C5A
0E7A0A8B960706FF1409B308F650D198
EE8C780DB70A3B97079DFE1499B308F6
50CA98EE8C120E850A4E98078CFE1421
B408F650C898EF8CD70D300A2E990789
FE1499B408F550CE98F38CA80E5D0AB6
99078CFE14FBB408F450C898EA8C0B0E
440AFC99078CFE143FB508F350CB98E6
8C880F620A1B9A078CFE1465B508F350
CC98ED8CCA0E260A219A07A6FE1468B5
08F350D098E58C2F0E7E0A119A07CBFE
1448B508F350CE98ED8C4C0E010AE099
071AFF140AB508F150DD98EB8C5C0D1B
0A7599073BFF14B0B408F050E098E98C
C30DB8090A990734FF1442B408EF50DA
98E88C970D330AD398072AFF14C6B308
EF50DE98E68C620DB20ABA980724FF14
45B308EE50E198E58CE30D830AAF9807
2AFF14C8B208EC50E998E98CEB0D090A
9E980727FF1454B208EB50E898EB8CA7
0D560A93980727FF14EDB108EB50FA98
E68CAC0D6A0A8A98071DFF149EB108E9
50F798E38C1810540A88980709FF1468
B108E850F498E88CE50E3D0A8A9807E2
FE1451B108E750FE98E58CFF0F600AAB
9807D8FE145CB108E750FD98E78C650E
4F0AC79807F9FE1487B108E750F998E2
8C360E850A9298073BFF14D5B108E650
F698F18C0D0E830A03980745FF143FB2
08E650E998F08C9F0D530A8D97072AFF
14B7B208E550F898F78C760D730A6097
0721FF1433B308E650E698E98CFD0E6D
0A5F970721FF14ACB308E650D598EE8C
E60D7E0A7A9707BEFE1414B408E650D8
98F28CD40DEF0A009807B0FE1461B408
E650D898F18C240E4C0A759807AAFE14
8FB408E550CF98EC8C1D0EA40AC79807
D5FE14A2B408E650CB98EC8CA80ED009
D29807D5FE1497B408E650C398EE8CE4
0D440AC3980706FF1474B408E650C998
EA8C0C10DF0A8D980759FF143DB408E5
50BA98F48C2E0E9C0A1F980763FF14FD
B308E550C298F18CD00D580ACA970763
FF14BDB308E450C898F18C920D240A9D
97075CFF1480B308E350BF98EF8CBA0D
360A8A97075CFF144FB308E350C998F0
8C1C0E470A7D97074FFF1429B308E250
CC98F08CE70D7E0A7E970731FF140EB3
08E050D598EE8C5A0D5B0A8D970734FF
14FCB208DF50CE98F38CAE0D290A9A97
0738FF14F0B208DE50D898EC8C9F0DB6
0AA397072EFF14E6B208DD50DA98F08C
350DB80AAA970745FF14D9B208DC50DB
98EE8C9D0F3F0A91970759FF14CBB208
DC50DC98ED8C000F720A5D970766FF14
C2B208DB50D198F58C800E8C0A2A9707
66FF14B9B208D950D698F08C680F790A
0997077AFF14B4B208D950C698F48CA8
0E8B0ADE960794FF14B5B208D750CE98
F38C1A0F820ABA960770FF14C5B208D8
50D398F08CC40E3D0ABD960770FF14E0
B208D750C698EF8C550F920AC0960755
FF140CB308D750CB98F98CF60D780AD0
960738FF1449B308D750C298E98C700E
490A05970710FF1490B308D750BF98F0
8CB00D5C0A5D9707E8FE14D7B308D650
C298F28CD20D4D0ACF9707E8FE1419B4
08D650C398F08C740E660A239807E5FE
144EB408D750C098F48CB60D4C0A4C98
07E5FE146CB408D650CC98EB8C760D0D
0A669807F9FE1476B408D750D898E68C
430E870A63980738FF1466B408D550CC
98EB8C0F0E760A2C98074FFF143FB408
D550DC98F18C0F0E4D0AE8970769FF14
05B408D450DE98F98C5D0E280AA99707
7DFF14C0B308D550EF98FA8CE50F310A
77970787FF1474B308D350ED98EE8CBC
10390A48970797FF142BB308D250E998
F18C550F600A1D970797FF14EFB208D1
50F298ED8C0B0E500AF8960791FF14C6
B208D150F098EE8C2D0F150AE8960784
FF14AEB208D150E998EF8C7F0E760AE9
960784FF14B0B208CF50EF98F08C1311
600AEB960752FF14C3B208CE50F498F4
8CBE120D0A0C97072EFF14E4B208CE50
F198F28CC113220A3397072EFF140DB3
08CD50F998F28CF00E3C0A3E970734FF
1432B308CC50F698F38C110E200A3897
0738FF1456B308CC500499F28C270EA7
0A2E97073EFF146FB308CB50F698F58C
290E580A26970742FF1481B308CB50F6
98F58CEB14B30A22970752FF1483B308
CB50F898F28CED16760A1A970769FF14
80B308C950F598F78CF316870A089707
73FF147BB308C950E998F68CE70F7F0A
F1960776FF1475B308C850E798F28CAB
0E490AE4960773FF1476B308C750D898
EB8C710F4D0ADC960776FF147AB308C7
50D898F68C8B0F140AD9960770FF1489
B308C750D398F08CE70F7A0ADC960763
FF149EB308C650DA98F08C290FA90AE8
96074BFF14B7B308C650D298F28CEA0D
840AF796074FFF14D5B308C750C898F5
8CEC0D190AF6960755FF14F5B308C650
CD98F48C790EF409E5960752FF1411B4
08C550D198F48CE80D150ADA960755FF
1423B408C350CD98F68C230F5A0AD496
0763FF142CB408C350D898F28CF30D2F
0ACF96077AFF1428B408C250DA98FA8C
F50D240ABE9607A1FF1413B408C150DE
98F98C650E4D0AA1960797FF14F1B308
C050E698FC8C410E280A94960794FF14
C3B308C050F198F98C400E7E0A8F9607
A1FF1490B308C050F198F68C0B0F590A
889607ABFF145CB308C050FD98F48C49
0E060A7A9607A8FF142BB308C050F498
F18CB70E350A6B9607ABFF1403B308BE
50FD98EF8CE20F160A629607A5FF14E9
B208BD50FE98F48C030F020B609607A1
FF14DDB208BD500499F28CD90FCC0962
96079EFF14E2B208BC500899F48C280E
880A6296077DFF14FAB208BA501D99F2
8CFD0D3C0A6C96074BFF141FB308B950
2699EE8C650E470AA1960738FF1451B3
08B8502199F78C360E640ACA96073EFF
1489B308B9502E99F98CE30D0A0AD496
0700FF14C5B308B8502699F78CEA10D6
09379707D1FE14FEB308B8503C99F58C
A50E680ABB9707ECFE1430B408B85040
99F98CBE0F280AF0970706FF1454B408
B7503D99F48C1E0E2F0AE497072EFF14
65B408B7502A99F58C1F0EB40AB49707
2EFF146AB408B6503099F28C9D0E9C0A
8C97075FFF145BB408B7502A99FB8C6C
0EB40A6397075CFF143CB408B6502799
F98C330E130A48970769FF140DB408B6
501799F78C270E350A3397076CFF14D4
B308B5501499F38C7D0EFA091C970776
FF1492B308B3500599EE8C1A136D0A17
970763FF144DB308B4500699F98C610F
060A2D97076CFF140CB308B5500799EF
8C2A0E270A2D970766FF14D2B208B450
0399EC8CB60E5E0A22970752FF14A0B2
08B250FF98F48C4A0E6B0A2F970738FF
1481B208B1500C99F28CA80E260A4D97
075CFF1473B208B1500399F38CD00E6D
0A4897074BFF147FB208B0500099F28C
320EAF0A4D970709FF14A2B208B0500E
99F58C2C0E960A7E970706FF14DEB208
B0500599EE8CDF0DF20993970709FF14
36B308AF500499F28C870D1D0A879707
17FF149DB308AE500099F48C130E140A
749707DBFE140CB408AC500799F78C03
0E940AAF9707D1FE147DB408AB500D99
F78C100E410AF79707A0FE14E5B408AA
50F898F38C970D1C0A5898078CFE1437
B508AA50FE98F78CDB0D4F0AB7980785
FE146DB508A950EB98F58CF30D350A14
99078CFE1483B508A850EF98F48CED0D
130A4A9907C1FE1477B508A750E698FB
8C270E650A2B990709FF1442B508A650
D598F78CD00D6B0AC398073EFF14E9B4
08A650D198F38C0B0EBA0A4998073EFF
1471B408A450D598F58CF10D5D0A0398
0742FF14E6B308A350C498F68C9F0DB4
0AC897075CFF1451B308A350C198F88C
500E6C0A8697076CFF14C4B208A150CA
98F48C340E180A4197077AFF144BB208
9F50BE98F68C1A0EC90A02970780FF14
F0B1089E50C498F98CE40E4B0AD69607
7DFF14BBB1089E50CD98FB8C0E0F240A
AC96077AFF14AFB1089E50CF98FD8C25
0E510A81960780FF14CCB1089E50D998
FA8C220E730A5E96076CFF1405B2089D
50E498FC8CB70E1D0A6296077AFF145C
B2089B50F398F88CC70DF9095D960773
FF14C2B2089C50EF98FB8CB60DE60953
960766FF142BB3089B50FE98F98CA90D
2C0A61960776FF1493B3089A500299F4
8C120F19096096077AFF14F6B3089950
0999FE8C540E6A0A5D96073BFF1446B4
0898500C99FA8C310EF709A79607D1FE
1482B40899500B99FF8C990E580A5297
07CBFE14A6B40899500699FB8C1F0E70
0ACF970709FF14B9B40898501399F58C
5B0E480AD5970726FF14BCB4089850FE
98F98CF80E150AAD97074FFF14B1B408
97500E99F98C450E600A6F970755FF14
9FB40896501599F88CCE0D830A409707
63FF1481B40895500D99F38C3C0EFC09
1E97075CFF145EB40895500E99F48C3E
0E310A11970752FF1439B40894501199
F48C260EAA0A14970755FF1405B40894
500C99F48CE90DE60915970766FF14C8
B30895500A99F68C3A0E2D0A0E970769
FF1486B30893501599F48C8511780A03
970769FF1442B3089350FF98FA8C720E
9E0AF7960770FF14FCB20893500699F5
8CA50D7F0AE896077AFF14BDB2089350
0399FA8C990D2D0AD8960784FF148FB2
089250FA98F78C850D5B0AC496077AFF
1473B2089150F598FB8C1A0E440AB896
0773FF1472B2089050EF98F68C6A0FB8
0AAB960776FF148CB2088F50E598FD8C
AD0F7A0A8D960784FF14C3B2088E50DE
98FA8C760EC00A56960784FF1415B308
8F50E998FB8C860E360A2C960770FF14
75B3088F50F898FB8C1B0E680A1A9607
70FF14E0B3088E50F398F58CB40D430A
2E9607E5FE1446B4088E50F698F98CF8
0E540AF3960706FF149EB4088D50F898
FB8CDF0D3A0A7A9707F9FE14D9B4088D
50F898F98C3B0E6E0AB19707D1FE14F5
B4088B50F198018DE70E3C0A0298071A
FF14F0B4088C50F698F28C290E440A03
980752FF14C8B4088B50F198F88CC90D
7E0AB197079EFF1480B4088A50F498F7
8C550F3B0A2D9707A1FF1426B4088950
E598F48C7E0E440AD7960797FF14BDB3
088950DC98F98C040F690AB3960797FF
1458B3088850E098FB8C900E5B0A9C96
079EFF1400B3088750DA98F78C240E64
0A829607A1FF14BAB2088650E098F98C
5F0FB10A669607A5FF148CB2088550DC
98F58CA60E440A4E960784FF147AB208
8450E098F88C750E930A57960787FF14
81B2088350D398F78C7A0E890A659607
7AFF149DB2088150D398FD8CD90F2F0A
7196075FFF14CEB2088050CB98F98C1F
10EF09A0960748FF1412B3087F50D398
048DB10E490ADA960734FF1459B3087E
50D598FF8C8A0E8C0A11970721FF14A1
B3087E50DA98F98CD20E470A529707F6
FE14E4B3087D50D298F78CFA0E440AAC
9707E5FE1416B4087C50EB98F88C9A0E
7C0AF79707ECFE1438B4087B50EF98FB
8C960E630A0E9807EFFE1447B4087B50
E698FB8C620F520A1D9807F9FE1449B4
087A50E298F98C8D104F0A23980717FF
143AB4087950E798F68CDC0E6F0A1498
0738FF1419B4087950E998F68C010F46
0AED97074FFF14F1B3087750E198FB8C
AA0E7E0AC097074FFF14C1B3087750E2
98FB8CE60D870AA3970763FF148FB308
7550E698F48CDE0EDC098A970769FF14
50B3087550F498F98CB80D040A6E9707
69FF14D4B2087650F098F88C950DE809
56970794FF143BB2087550FC98FC8CFF
0D770A0F9707C9FF14A1B10875500499
FB8C470EB50AB49607D9FF1421B10875
500499FD8CDB0F920A5E9607D9FF14AF
B00874500899FD8C240E8D0A1B9607D6
FF144FB00874500F99FC8C380E330AE7
9507E3FF14F8AF0873500499048DD60E
3E0AA39507F4FF14A5AF0873500A9908
8DC712700A599507F1FF1453AF087150
0799FF8C560F630A2C9507FAFF1400AF
0872500D99FC8C960E850A0995070400
15A4AE0872501199028D1C0E790AE694
0704001540AE0871500799FE8C020E7A
0AD194070E0015D4AD0871500099048D
B90D370ABC94074300155EAD0870500B
99FF8C590F420A7C9407A90015DCAC08
70500599018DBB0E420AEA9307CE0015
54AC08705006990B8D3F0E8F0E629307
DE0015C0AB086E50FB98098D7E0EF309
079307F2001528AB086D50F698FF8C31
0E420AC092070601158AAA086C50F498
048D980EF9098592070C0115F3A9086B
50FA98068DD80D2D0A56920741011563
A9086A50FC980A8D7B0E3F0A06920755
0115E0A8086950F898098DF90D1B0AB2
91076901156AA808695001990A8DB60F
760A689107800115FFA70867500C9908
8D840F5A0A239107AB0115A4A7086750
11990A8DC00E400ABD90071B02154EA7
0866500D990F8D8F0E210AF58F075D02
15FEA60865501199138DA70F680A2B8F
07530215B5A60865501999178D2B0E67
0ABD8E0767021573A60863502499098D
EE12370A678E078F021531A60863502C
99118D210F640AFE8D070C0315F2A508
635032990E8D2B0E320A3F8D07340315
B7A508625034991A8DD50E830A938C07
3103157CA50862504499158DBF0F390A
408C071003153DA50862506099158D8C
0E3B0A3A8C07270315F9A40861506299
1B8D36136A0A2C8C07AB0315ABA40861
508599178D7E10A10AB38B0797031558
A408625085991D8D200F860A658B07C6
0315FBA308615090991E8D390E7F0A0C
8B0736041592A3086050A299218D5A11
2F0A708A074004151DA3085F50B49924
8DF20EE30A028A074A04159DA2085E50
D699278D60107D0ABA89078F041512A2
085C50EF99218D620F020A518907EC04
157AA1085B50FD99288D830F000AB988
07480515D7A0085A50129A298DC80E4C
0AE98707AC051529A0085A50249A268D
6C0E7C0A0A8707E70515719F08595037
9A248D970E330A508607190615B49E08
5750409A268D970EF009B285075E0615
F69D0856504A9A288D180F720A118507
9706153F9D0854504F9A2F8D050F310A
7E8407D90615919C085350739A288DBE
0E370AF48307FD0615F69B085250829A
298D440F5E0A7283072F0715709B0851
50949A2C8DBC10360A06830782071506
9B084F50A69A318D6F0F6B0A818207FF
0715AF9A084F50B19A338DC80FB80AB8
8107240815779A084D50B99A2C8D2C10
420A188107240815529A084D50C59A31
8DC00E2B0AD180072408153F9A084D50
C69A358DA20F0A0A958007EB0815349A
084D50D29A338DC60EBF0ACF7F07BB09
152F9A084C50D49A358D3C0F970A877E
07E60915249A084C50E09A358DCC0F15
0A7D7D07F00915099A084B50E69A378D
F30E530ADF7C07D90915D699084A50F1
9A338D030F550AAA7C079A0915869908
4A50FE9A378D240F170AD37C076C0915
1699084A50089B3A8DFC0ECD0A267D07
8609158798084A50199B3A8D430F3C0A
477D07A70915D997084950179B3C8D39
0E4A0A357D07CC09151697084850269B
408DB50F440A037D07E6091543960848
502E9B3A8D3A0E710AC27C070B0A1567
950848504D9B418D330E470A787C071A
0A158C94084650619B3E8D270F0E0A3C
7C07250A15B593084550839B408DDD0E
4D0A0F7C072F0A15F292084650929B3E
8D3F0F7D0AEC7B07360A154592084450
9D9B3D8DB80E6F0AD37B07320A15B991
084350B79B428DDA0F120AC57B07250A
154A91084350BA9B3A8D4211F009C07B
071B0A15FD90084250CE9B3F8D7E102C
0ABC7B07290A15C190084250D29B3B8D
570FD40AB57B07290A159690084250DE
9B418D550F360AA87B07500A15719008
4150E99B418D3D105D0A7C7B07820A15
4A90084150E89B368D8510900A267B07
850A151990084050F59B3E8D4F0F0B0A
D27A07D50A15D88F084050FB9B458DF4
117A0A787A07E20A15808F083F50FE9B
448D0E10B60A317A07E50A15118F083D
500B9C468D180F580A117A071A0B1590
8E083D50149C4D8D2C10410AD7790771
0B15008E083C50319C4B8D350FB00A60
7907B30B15698D083C503A9C468DF90F
1C0AD27807F50B15D28C083B50569C4B
8DFE0E0D0A3E78074B0C153B8C083B50
5B9C518D8D0E2B0A9D77077D0C15AD8B
083C50749C4C8DDB0F6F0AFA7607050D
15288B083A507D9C558D540F9A0A3276
07090D15AF8A0839508C9C528D7D0E7B
0A9F7507540D15418A0839509B9C558D
CF0EDE09137507AB0D15DD89083750A4
9C4E8D9810FF0A6A7407C20D15828908
3750AA9C588DFE116B0AD77307680E15
2B89083550B89C4E8D0210EE09097307
BF0E15D988083350C69C518DF80E7C0A
2B72074A0F158388083450DA9C5A8DCA
0E260A5D7107DC0E152688083350DE9C
5B8DA40EA509237107E30E15B9870833
50DC9C558DB90E0C0A1B7107780F153F
87083250DC9C5B8D1A0F420A9B7007AD
1015B586083250E49C638DA60F760A63
6F07F610152086083150D79C5E8D6D10
C70A546E074911157E85082E50D89C5C
8D7E0F3E0A886D07C81115D984082D50
E09C618D15103B0ABB6C074D13153784
082C50D89C648DD30FF510246B072B15
159983082B50E89C678DB30F6B0AFC68
077515150A83082B50F59C708DCA1142
0A3A6707C017159482082B50FF9C6F8D
7112730AD86407D21B153282082A502A
9D758D05125B0A0A6007662715EF8108
2950299D7A8DF211840A055607FB2215
BE81082850509D7C8D36125A0ABD5007
602915A181082850529D948D5013060A
BD4A070E34158D81082650939DA28D78
12730AB33F071C3E157881082650AF9D
B28D1A123C0ADF3207883F1559810825
50D09DBB8DBC112B0A7A280794441529
81082550069ED08D3A124B0A05210705
4315DE80082450449EDD8DFD12570A8E
1D073A40157580082350799EF08D3512
710AAC1D07624215ED7F082350AB9E01
8E11144C0A101D07884515447F082350
EF9E0C8E8F13320AD41A078044158A7E
082350219F218EC814770ACD1907DE45
15C07D082250749F258EE114530AAA18
07A34915F47C082150BF9F298E671764
0A751507984E152D7C0820500EA02D8E
EA1B3A0A741007075015757B081F5072
A0308E8219370A380C07095215D17A08
1F50E0A0358EE819440AC808076E5315
3F7A081F503BA1358EFD1C2F0ADB0507
E45415C279081F50B1A1378E93187C0A
5E03070258155479081F5007A23E8E2E
27710A550007A35815F778081F5078A2
3F8E7222780AF3FD06C35815A978081D
50CBA23E8E64313B0A95FC06D25A1563
78081B5014A3498EBE2DF609DDFA068B
5B152678081B506FA3498E8F22680A25
F906E75B15F377081B50D2A3498E4F21
A60AF6F7062F5C15C677081B502DA44E
8E2C1F960A2FF706625C159777081A50
7FA4578EA31D8B0A7EF606D45D156C77
081A50E1A44D8E7D1AD10A59F506285E
153C7708185030A54F8EDA1DAD0A54F4
06365E150D7708175095A5568EE71D49
0AA8F306B15E15D676081750EBA5588E
6824460A06F306C25E15977608165034
A65C8E2A22610A80F206CB5E15467608
15508CA6598E9E25780A33F206185F15
E475081450BAA65D8E1A24860ADDF106
525F15677508135009A7678E751F510A
85F1067B5F15D37408125058A7668EF9
1F8E0A3DF106775F15277408125090A7
658E541E340A10F10615601564730812
50CEA76D8E291D7E0AA6F006AF601591
72081250FAA76F8E7B1E4D0AF1EF06A8
6115B37108125030A86B8E621C6F0AEB
EE06356215D5700811506FA86B8E7122
150AF3ED069162150270080F50A5A86F
8EC220690A32ED06916215486F080E50
E5A8678EE120B60AC5EC06F86215A66E
080C502FA96B8E72302E0A57EC06A663
15276E080D506FA96E8E8222490A9FEB
062A6415CA6D080D50B2A96E8E5F2DA3
0AD5EA068564158F6D080D50ECA96B8E
F52F390A2AEA06A464156F6D080D502F
AA698EA027790ABAE906A66415676D08
0C5063AA6D8EF027880B7AE906CD6415
636D080B5076AA6B8EE424980A3DE906
1165156D6D080950BBAA658E9220E409
F9E806566515706D080850AAAA718E7B
226A0AACE8067865156B6D080650DEAA
728ED6272A0A6FE806566515536D0806
50E5AA728EB82B760A5DE8061F651526
6D08065004AB718E4625790A77E8061F
6515DC6C0805502CAB738E5E23780A91
E8061E6515796C08055050AB6B8E311D
620AA7E806EC6415FD6B08055067AB72
8EBA24720AC8E806F16415686B080550
8AAB758E4F20C10AE1E806F36415C06A
080550B1AB778E5B21250AEFE8060B65
15046A080450CDAB7A8E0220800AEDE8
062B65153A69080350E9AB758EB61F19
0BDDE80634651563680803500AAC7A8E
261DA50ACDE806766515876708035027
AC788EB821980AA4E8069E6515A86608
025030AC778ED223440A71E806AF6515
CF6508015042AC798E19222B0A52E806
C16515056508015062AC6F8E49217E0A
3BE806C765154B640801505DAC758E15
205A0A23E806DB6515AB630801507EAC
728E7021300A13E806ED6515246308FF
4F97AC778E7D1D960AFFE7060C6615BC
6208FE4FA9AC728E1F38AE0AE0E7060C
6615756208FD4FB2AC748EDC2C3F0AC7
E706056615436208FC4FD2AC738EC623
690AB5E7060C66152C6208FB4FE6AC76
8E2620B00AB0E706086615236208FA4F
ECAC738E1520280AABE706F765153362
08FA4FF4AC718E573C4F0AA8E706FC65
154B6208F94FFDAC728EDE369A0AA6E7
06FA6515636208F84F0EAD748E5B2859
0AA5E706FC6515766208F74F14AD728E
9C28530AA5E706016615816208F64F1B
AD778EB825400AA6E706D16515766208
F74F22AD748EEF273D0ABCE706D56515
4C6208F64F19AD748EAA22DE0ACAE706
ED6515046208F54F2BAD718E8424620A
CCE706BB6515936108F44F34AD6F8E2D
22570FDEE706A86515FF6008F34F39AD
6F8E4722080AF2E706B66515476008F3
4F47AD778EC421ED09FEE706B4651577
5F08F24F3EAD748E8F23450AFFE706CA
6515925E08F24F42AD728E18215A0AFC
E706D16515A75D08F24F48AD7A8EE122
7E0BF4E706D56515BC5C08F14F5CAD75
8E4624570AE7E706E26515DB5B08F14F
6FAD7B8EF520600AE0E706DE6515085B
08F14F7AAD728E9924A90ADCE706E965
15445A08EF4F90AD728E65238B0AD9E7
06E26515895908EF4FA4AD758EB4217E
0AD3E706DF6515E35808EF4FABAD768E
CC20590AD4E706D165154C5808EE4FBA
AD728E5729FF0ADBE706C86515CC5708
ED4FBAAD738E7530730AE6E706B66515
625708ED4FB6AD748E2028110AF5E706
4C65150F5708ED4FC1AD748EDF255E0A
04E806946515CF5608EC4FBDAD6E8E26
24B30A12E8069B6515A55608EB4FB2AD
7F8E3F24370A18E8069D6515895608EB
4FA8AD7A8E8C24D60A16E806AF651574
5608EB4FA4AD7A8EC71B7E0A08E806CB
6515695608E94F9DAD738E542ACE0AF5
E706CA6515595608E94F9EAD7C8E4320
2A0AEBE706D16515415608E84FABAD75
8EB923700AE3E706EB65151D5608E84F
9CAD788E1625380AD4E706D86515E655
08E64FADAD788EC421280AD4E706C165
15A15508E64FB2AD768EDB27430ADFE7
06DC65154B5508E64FB7AD798E2F2065
0AD7E706056615EB5408E54FB8AD7B8E
9F206B0AC2E7061666157F5408E34FCA
AD748ED823560AABE7060C66150C5408
E14FD2AD788E49200E0AA1E706056615
945308E14FEAAD788E48278A0AA1E706
126615185308DF4FEFAD7A8EDF26D80A
9CE7060F6615955208DD4FE8AD7D8E10
22150A9AE7060F6615075208DD4FEFAD
7C8E9621360A9BE7061666156E5108DD
4FF0AD7A8E5820920A94E706306615C7
5008DC4FF9AD788ED425D80984E70631
66150F5008DB4FF0AD848ED322570A76
E7062A66154C4F08DA4FE8AD7B8EC721
4B0A74E7061F6615834E08D94FE4AD7C
8E1521320A7BE706166615B74D08D84F
DFAD7B8E991E7E0A80E706196615F14C
08D94FD0AD7B8EAA25060B82E7063664
153B4C08D84FCCAD788EE7238B0A7CE7
063166159F4B08D74FC5AD7C8E4B2949
0A73E7064066151A4B08D64FC6AD838E
DE20530A65E7063C6615B14A08D74FC7
AD818E75255E0A5EE706366615694A08
D74FD7AD778EA42D640A54E7063F6615
344A08D64FE8AD818E123AFB0A4BE706
5E66150B4A08D64FFBAD7F8EDA3E9C0A
2EE706846615EE4908D54FF8AD848EA0
29910AF7E606516715D54908D64F04AE
818EB6238F0A68E606966715B94908D5
4F08AE7E8E4425250ACFE506D4671599
4908D54F26AE7A8EE328350A4BE5067C
68156A4908D64F1DAE838E57270312AC
E4069E68152C4908D54F09AE848E2D24
3E0A1CE4061E6A15DF4808D54FFDAD84
8EC723580A13E306726B157E4808D44F
09AE888EAB23A50A8DE106986D150848
08D34FF0AD8D8EDA23330A83DF06836D
15814708D24FF6AD948E75225A0A10DE
062F6F15EC4608D04FF1AD9E8E2A2289
0A9ADC064671154B4608CF4FE2AD9D8E
EA21870AB4DA068A7215AD4508CE4FE8
AD9E8E8A22910ACCD806667315194508
CD4FF0AD9E8E461F0B0A2BD706717515
964408CD4FF6AD9F8E861ECC0A36D506
017815264408CC4FF9ADA38E0D1D560A
D1D206BB7915D34308CC4FFFADAB8E4C
1E5E0A64D0069B7C15904308C94F02AE
AB8ECC1D2C0A3ECD06E37F155B4308C9
4FFDADB28EB01E980A7FC90617821526
4308C84F17AEB78E581F980A26C606EC
8315E14208C64F32AEC08E201B840AD1
C2062B8B15834208C54F3EAEC58E881C
5E0AB2BD06378C15044208C54F4BAED4
8EED1A4F0A4BB906CD8D15614108C44F
5FAEDE8E4E1B940A51B606D69015A040
08C44F72AEDE8ED0190E0B6DB3064094
15CC3F08C44FA8AEED8EBF18950AECAF
063E9B15EF3E08C64FC8AEF18ED61851
0A69AA06F3A515183E08C44FF3AEF28E
2718420A27A2066EB1155A3D08C34F1B
AFFF8E8A18580A17980622BA15C63C08
C34F4BAFF98EDE18AB0A6A8D064CCE15
6C3C08C24F88AF048F081D7D0A087F06
F6E515443C08C24FC4AF038FED199E0A
736C0697E315493C08C04FFDAF088FA4
19A40AF06006C8E1155E3C08C04F36B0
088F4B1A490B945A061D0216793C08BF
4F7DB0128F7319200AF04D067CF41599
3C08BF4FB9B0168F271C4F0A84450650
1A16BC3C08BE4FD8B0208F2A1A610AD8
3506AF2016DD3C08BE4F26B1208FA71C
AA0AA42606982616F63C08BD4F7CB117
8F891B3F0A751C06EB2716093D08BB4F
E0B1208F731B4C0A5116069C2616153D
08BB4F0FB2268F5119350AD113066026
161B3D08BA4F41B2208F441A8F0AEE12
062D2516163D08B84F92B2248F6E1A87
0AE71206B92816043D08B94FC1B22F8F
FB181B0ABB1106C22916DB3C08B84FFC
B2258FF81A190A4A1006AE2816963C08
B74F42B32A8FAD19890AC70F06112816
303C08B84F7DB3288FD1188F0AE90F06
1726169E3B08B74FB5B3318F13186D0A
9E1006CB2716DA3A08B64FE4B3388FC5
17550A721006E42916ED3908B54F0BB4
2D8F7C16090A440F06E62C16DC3808B5
4F2FB4348FCD15C00A490D066D3016B8
3708B44F58B43A8F4315870A540A0611
3416893608B34F66B4348FEA14350ABA
0606143516663508B24F73B43E8F2215
F70A6102064E3E165C3408B14F88B444
8F0215880AE8FC05943F167D3308B24F
B0B43B8F6314150A84F8050D4116CB32
08B14FC4B4498FC914A80A43F505D946
165D3208AF4FE7B4498F1014A80A08F0
05375116353208AE4FF6B4498FE4138D
0A5AE705E44F163C3208AD4F1EB5498F
EE149A0A7EE1055B5616663208AC4F30
B54E8F40154B0A45DB05435C16A73208
AC4F62B5508F4715820AB8D305F06116
083308AA4F6FB54C8F5814530A05CC05
F46216733308AA4F91B5588FD813440A
AEC605A96216D73308AA4FB8B54F8FDC
13A90A05C4051E6216263408A94FBDB5
498FFD135C0AFEC205C961166B3408A7
4FEDB54F8F5713730ADBC2055A6116A2
3408A74F12B64B8FD313670A18C305D0
6016BC3408A74F0FB6478FAC146F0A8D
C305396016B83408A74F16B64C8F8416
830AECC305106116923408A74F3DB645
8FAB14650A08C405BD6016423408A64F
3DB6408FA6156E0A44C4051D6016C733
08A54F38B6408FF4146C0ABBC4056860
16213308A54F2CB6428FB9145F0AF1C4
05E26016503208A54F1EB63C8F6F14B3
0ACFC405F36016573108A44F32B6458F
0B14CB0AA6C4052561163A3008A54F26
B63F8F6D13BF0A7AC405096216142F08
A44F2EB6418FF712990AFFC3056D6316
EC2D08A44F3FB6458FDC12AB0AFFC205
956416D82C08A44F4EB63C8F1D13860A
C0C105C26616FD2B08A24F61B6438FC0
12840A0FC005CB6816442B08A24F65B6
378F0B127F0AEEBD057B6F16AD2A08A1
4F63B6388F43126D0AA1B905DE7B165B
2A08A14F64B62E8F8413500ADBB00594
8516602A08A04F73B6328FA413B30AEE
A7056D7916C12A089E4F65B63A8F5313
290AD5A605097B16672B089D4F81B632
8F7D12340A4BA7050C7D162B2C089C4F
B0B6338FA513900A75A6052481161B2D
089B4FADB6338F34137E0A33A305269C
16392E089A4FC4B6368FDF129F0AF496
05EE9F16352F089A4FCFB6368F1213AE
0A368D057C89162830089B4FE4B6318F
95136A0AD28F05CB7D16D13008994F03
B73A8F1813240AF99805DA7B16223108
994F22B72F8F4813C30AB79F05A47C16
073108984F3BB72A8FD2139E0A27A305
C67F16E23008984F40B7318F5713250A
69A305988116C83008984F21B7358FE6
13960AB1A105848816773008984FEAB6
338F60132A0A0D9E05B98B16E82F0897
4FADB6328F0614510A949A053E851627
2F08974F84B6308F6613D70A219B0503
8316382E08964F63B63B8F73135C0A16
9D056C8116252D08964F44B6318F2413
980A029F05E87C16EB2B08964F20B631
8FDD12930A14A205827C169F2A08964F
13B6338F4E12C10A5AA405AE7E167429
08964F07B62B8F2E1249FF52A405E781
166F2808964F04B6278F0B12DFFE06A3
058A7D16A52708954FF4B5188F9C1CE2
FEDAA20594F414622708934FE6B5F98E
BA1EE4FEAA9E057CB80D652708934FAE
B50D8FDA1ED9FE599B05F7F40C642708
914F6EB51D8F281FE1FE6E990593C70B
642708904F25B52B8F321FE5FE2C9805
CBB80B652708904FE0B42D8F591FD5FE
AA960505740D7B2708904FBFB4298FC3
1BE3FE6D950516E2130C28088F4FCAB4
228F2C13D7FEF78E055AA516D828088E
4FD4B42D8F51124CFF3085052AA616B6
29088D4FD7B4248F43128E0A987E05F7
A516882A088C4FCDB4288F3712FD0D01
7B0503A416402B088D4FC5B4318F6312
8F0E547905E2A216F82B088C4FACB42B
8F2912270AC77805ED9D16A42C088B4F
95B42C8F31139A0ACD7805219B16242D
088A4F75B4318F3412BA0A357905409A
16782D08894F2EB42B8F73126B0A297B
05A89716A42D08894FBDB32D8FF112E3
0F1B7D05C79716AD2D08894F18B3298F
6C13980AFD7D052B9716912D08884F5A
B2298F4F13BA0A397E05D695164B2D08
884F6FB1308FDF127A0AC67E058E9216
E12C08884F70B02D8F9A12C10A7F7F05
D68F16582C08874F3DAF2A8F8B121E0A
AD7F05E98D16BC2B08864F05AE2D8F19
13830A8E7F051B8C16092B08864FCBAC
298F5A13480A857F05A78B16462A0886
4F7EAB2D8FBB12DC99A67F05DC8F167B
2908854F28AA2A8FBC12CC44C87F05EF
8F16BB2808854FD8A82F8F6912CAFE14
80053A8C160C2808834F79A7358F5012
D7FEB78105699216842708824F1AA61D
8FCC1CDCFE4F8705968D16602708814F
ADA4108FE61ED8FE048C05737B166527
08814F95A3238F381FDAFE8D92050A72
167E2708814F03A3208F591FE2FE8F9D
05426F16FB2708804FDAA2258F5214D8
FE39A705716F16A128087E4FE9A2308F
3012CBE8EAAB053687165929087F4F4A
A32C8FB111C709CBA20553A0161E2A08
7E4F14A42D8F1F127E0C3B930574A416
E62A087B4FF7A42A8F73129C0A808705
EDA216932B087A4FAEA52A8F88129A0B
DD80056FA116312C087B4F5CA62E8F4D
12690B697D05F4A016B82C08794F2BA7
388F1C12C30AB97B0595A016252D0878
4FD8A7338F19135E0EF67B05259F1672
2D08764F6AA82C8F8212FD082E7E0568
9C169F2D08764FEAA8338FA912A10B9F
80052B97168A2D08764F5BA9318F1C13
1743968205D19416102D08754FA1A930
8F0513640C4B8405D69316542C08744F
B8A9338F7F123C0A528505A99316742B
08734F9BA92F8FC212640A118605A893
167B2A08734F50A9318F00125D0A7886
058E92166C2908724FC4A82F8FAD12CD
C88286053C9116572808714F2CA8338F
3012DAFE9986058092167F27086F4F5E
A7108FCA1CA6FEDB88050B8F16612708
6E4F93A6088FC01EE4FE408C05997516
6527086F4FC2A51E8FFD1ED6FE939305
DB6C166427086F4F51A5278F161FE1FE
34A105E253156427086E4FDCA4308F20
1FDCFE73AC059E2B0E6327086D4FA3A4
388F2A1F57FFB2B20578830F6327086D
4F58A43A8F021F79FC69B505E2A20D64
27086C4F24A43D8F281FCECD9EB6051E
C70C6327086B4FFFA3408F171F0BAD35
B7052D600C6427086B4FF4A3418F1B1F
C2697FB705BA510C6327086B4FF3A349
8F041F763DA9B7057E150C6427086A4F
1DA44B8F171FCD2DC7B7051EF80B6327
08694F40A44D8F381F4427E4B7055E14
0C642708694F76A44F8F761E852106B8
0577080C642708684FB1A4568F051F00
2029B8055F250C642708674FE6A45E8F
481FC71F49B80556570C632708674F30
A55B8F701F262159B80577890C652708
674F67A55F8F7A1FB92144B805ADAB0C
642708674FA8A55C8F5E1F28222CB805
1EB90C652708654FEFA55C8F661FBA22
28B805411E0D652708654F2BA6618F78
1FF32235B80506820C632708654F71A6
6B8F621F77237EB8050DBF0C63270865
4FAEA66C8F611F1A241AB90575090D65
2708654FD2A66F8F601F7E248FB9053D
E90D632708644F13A7618F661FDD24BC
B90543E50E652708634F43A7608F631F
A52504BA05AE0A0F632708624F6EA75E
8F6F1FA6254EBA0542420E632708614F
A8A75C8F711FDA2584BA059D150E6527
08614FC6A7608F771FE625A8BA056CB3
0D652708614FDCA76B8F711F0F26C7BA
05AA180E652708614F01A8768F781F1A
26F0BA055F380E642708624F16A8768F
721FC2251CBB0564870E652708614F34
A8808F7A1FAB2549BB0570590E652708
5F4F57A8858F601F7E257BBB05E6910D
6427085E4F63A8918F631F6425C6BB05
1D7D0C6327085E4F7BA88E8F8B1F9425
5FBC05D2680C6427085D4F90A8998F75
1FB725DFBC05F5A90D6527085C4F96A8
A58F5D1F60251EBD05737C0D6127085C
4FABA8B08F651F872554BD056F500D63
27085A4FB8A8B78F481FFD2590BD0516
B60E6327085A4FD1A8BC8F4B1F6925D1
BD05196C0E6427085A4FD3A8C08F811F
B42519BE05F0BA0D632708594FF0A8B2
8FD31FEF2565BE059AAF0D642708584F
04A9A78F331FCE25B2BE0530AB0C6427
08574F0AA9928FC91E3E25F7BE051936
0C642708574F18A9748FAA1EAE2537BF
0562A40E642708564F28A95E8F831DA1
257ABF05497F0E642708554F41A9588F
451E9825C6BF05CB680E652708554F43
A9518F2A1F612523C005A8EE0D642708
554F4BA9538F621FFF2477C005A5DB0D
622708554F53A95A8F641F1525C4C005
A0560D622708554F50A95C8F891FC424
FFC00590130D632708544F65A96D8F6F
1F112536C105AD8E0C652708544F71A9
708F6F1F83248AC1056A220C63270854
4F81A9748F821F962435C205F4930C62
2708544F82A9748F6A1F5E24B1C2055F
9E0C622708534F8CA97D8F7E1F32241A
C305104C0C622708544F93A9768F6F1F
942463C305E7D00C642708544F94A984
8F731F552497C3056A0B0D612708534F
A4A98F8F801F7424CAC305C7BD0C6227
08524FA5A9A38F7C1FC423FEC30584F8
0B622708514FBBA9A98F851F162447C4
05B6B90B6227084F4FC7A9B78F6B1FCC
2374C405F93A0D6127084F4FC9A9BB8F
761F962392C4050CDC0C6027084F4FD1
A9AE8F821F9123C0C405075A0C5F2708
4E4FDDA9B58F801F4423F1C40522E70B
6127084D4FE6A9BF8F821F63231EC505
17B80B6227084C4FF8A9D58F811F0B23
4BC505B9620C6027084C4F11AAE28F7E
1F382375C505FF930C6027084C4F12AA
EC8F6A1F13239DC50534A40C6227084A
4F22AA0790891F8822C8C505E39F0C63
27084A4F1AAA1890801FAC22F4C50594
950C642708494F29AA2690861FF4221D
C60503750C642708484F32AA3690751F
942249C60560620C632708474F60AA40
90761F4B2273C605CA130C642708474F
51AA4B90811F3522A4C60520130C6427
08474F23AA49907E1FDD21DDC605E084
0B632708474F67AA4B907A1FC0211FC7
0599050B642708474F6AAA4D90711FDD
2161C705AFC90B632708464F74AA5290
661FCA2195C705157D0D642708454F72
AA5590871FA921C4C7051AB30D622708
454F74AA5590941F7921FAC7052C7F0D
632708444F73AA58908B1F3A2130C805
0BAD0D632708434F76AA5690771F5521
5EC805C5960D642708414F6EAA5E9078
1F5E217FC805B9520D632708414F76AA
6390961FFB2097C80574130D65270841
4F76AA6890911FFE20ACC8052A340C63
2708404F70AA6E907E1F3D21BDC8057F
310C642708404F76AA5690751F9220CC
C805D2D20B632708404F63AA50909C1F
8E20D8C805882F0B6327083F4F74AA50
90821F9F20D5C805FCC70B6327083F4F
C7AA53907E1F4D2059C805AE360D6327
083F4F84AA5790981F2D20FAC60534AD
0D6427083E4F61AA59907E1F502019C6
056F4C0D6327083E4F8FAA6390841F09
20F7C50544B90C6327083D4F7BAA6B90
7A1FF71F1FC60505620C6427083D4FB4
AA70907B1FB01F53C60520F50B652708
3C4FB7AA7B907C1FC61F93C605FEB30B
6427083C4FD4AA88905F1FAC1FCFC605
0ABA0B6427083C4FD2AA81907C1F561F
0DC70595EA0B6527083C4FCFAA8D9089
1F3B1F48C705A80F0C6527083A4FD5AA
8D908F1F4E1F85C70595110C6427083A
4FD8AA8890911F4D1FBFC7056E2D0C64
2708394FD6AA9690871F131FFDC70570
4B0C662708384FDEAA9290891FCB1E37
C80585480C652708374FCEAA9190771F
4B1F75C805E1410C662708364FDBAA94
90811F671EB0C805EC1B0C642708364F
D8AA88907E1FAA1EE7C80507D20B6727
08354FC7AA8F90871FA81E22C90581B4
0B642708344FC1AA90908E1FAF1E4CC9
05AD760B632708334FAFAA84907B1F77
1E72C90545700B632708334FC3AA8D90
8B1F6E1E89C90521780C642708314FAB
AA8490801F611E74C905DA3E0C662708
304FC3AA8090821FBD1E54C90522180C
6627082F4FC6AA7E90801FAE1E42C905
73D60B6327082F4F95AA8190951F3C1E
1BC90569BD0B6427082F4FBDAA839079
1F3A1EDBC8058A9A0B6127082E4FC0AA
8390841F1D1EB7C80596680B6527082D
4FBEAA84908E1FFF1DC5C8050D610B61
27082D4FB3AA88907E1FDB1DAEC80546
4D0B6527082C4FCFAA8A907C1F061E6E
C80550460B6227082C4FCFAA9790871F
2A1E72C80543500B6527082D4FDFAAA1
90661FED1D8CC80503460B6627082C4F
D9AAA4907D1F2D1EB6C8058B3D0B6427
082A4FE7AAA690871FDA1DE4C805C138
0B632708294FE8AAA4909F1F0D1E12C9
05D7390B632708294FE6AAAA909A1FA9
1D46C90538490B632708274FEFAAAD90
831F0D1E76C905824C0B642708274FFA
AAAF908B1FBC1DA5C9059C490B642708
274F02ABA8908D1FAA1DD6C9056D420B
642708274F02ABAF90831F361D05CA05
133B0B642708264F0CABAC90981F991D
33CA0523320B632708254F13ABB29081
1F291D63CA0585280B642708244F1AAB
B490811F281D91CA05F41E0B63270823
4F19ABC2907E1F9F1DBDCA051C160B62
2708224F2BABCC90941F121DE8CA05D7
100B632708234F26ABD7908B1F151D11
CB05141D0B632708224F2DABE390951F
F71C32CB0597220B642708204F39ABFC
90891FB21C49CB05D0250B6427081E4F
37AB0B918E1F011D62CB05BD380B6327
081E4F37AB2091711F131D73CB05D629
0B6527081E4F50AB2691861FD91C8ECB
0598220B6327081C4F44AB3091941F91
1CA5CB05EF1B0B6327081D4F51AB3691
A91F651CB5CB055C0D0B6327081C4F58
AB44919F1FCA1CCACB051B0E0B632708
1B4F5BAB3F917C1FB91CE2CB0574030B
642708194F63AB3691771F631CFFCB05
7EFF0A652708184F5CAB3491801FA81C
16CC0533040B632708184F61AB39917A
1F5A1C30CC0542020B632708174F6BAB
3F91B61F8C1C46CC050C080B64270818
4F66AB47919C1F711C5ACC05032A0B63
2708184F61AB54918F1F541C75CC0507
2B0B652708174F5AAB5291871F3A1C8D
CC05C8200B662708164F62AB4E91901F
061CA7CC05920F0B652708164F69AB49
91871F201CC0CC05F5FF0A662708164F
59AB4791711F301CDCCC05F8F10A6427
08164F61AB3E91761F4D1CF1CC0558E8
0A642708154F6AAB31918D1F921CC7CC
0599DE0A652708154F6AAB1E918F1F91
1C80CC05A2E00A642708144F6EAB0891
8C1F311C79CC0519E30A662708144F7A
ABFE909B1F451C7ECC0547E10A652708
144F7FABF590821F591C8CCC05C9DF0A
642708144F81AB0091911F001C9BCC05
9FDD0A652708144F8BABFB908B1F461C
ACCC05AEDA0A642708144F81ABF8909B
1F2B1CBDCC05E9D60A632708134F91AB
FB907C1F341CC4CC05E4D20A65270813
4F98ABF590921FFE1BC9CC0528CF0A63
2708124F91ABF790981FF91BD5CC05D5
CB0A632708114FA2ABFC907A1FE71B</Data>
   <DataCRC>4e4de834</DataCRC>
   <BytesSent>40223</BytesSent>
</SBEDataUpload>
</InstrumentRawData>
</SBEDataUploadFile>
